Workbook

Sheet Provider
A1: First Name | B1: Last Name | C1: Gender | D1: Professional Suffix 1 | E1: Professional Suffix 2 | F1: Professional Suffix 3 | G1: Specialty 1 | H1: Specialty 2 | I1: Specialty 3 | J1: Specialty 4 | K1: Specialty 5 | L1: Patients Accepted | M1: Practice Name | N1: Location 1 | O1: Location 2 | P1: Location 3 | Q1: Location 4 | R1: Location 5 | S1: NPI Number | T1: Headshot Link | U1: Education 1 | V1: Education 2 | W1: Education 3 | X1: Education 4 | Y1: Education 5 | Z1: Professional Statement | AA1: Board Certification 1 | AB1: Sub Board Certification 1 | AC1: Board Certification 2 | AD1: Sub Board Certification 2 | AE1: Board Certification 3 | AF1: Sub Board Certification 3 | AG1: Board Certification 4 | AH1: Sub Board Certification 4 | AI1: Board Certification 5 | AJ1: Sub Board Certification 5 | AK1: Professional Memberships 1 | AL1: Professional Memberships 2 | AM1: Professional Memberships 3 | AN1: Professional Memberships 4 | AO1: Professional Memberships 5 | AP1: Awards and Publications 1 | AQ1: Awards and Publications 2 | AR1: Awards and Publications 3 | AS1: Awards and Publications 4 | AT1: Awards and Publications 5 | AU1: Hospital Affiliation 1 | AV1: Hospital Affiliation 2 | AW1: Hospital Affiliation 3 | AX1: Hospital Affiliation 4 | AY1: Hospital Affiliation 5 | AZ1: Additional Languages Spoken 1 | BA1: Additional Languages Spoken 2 | BB1: Additional Languages Spoken 3 | BC1: Practice Cloud ID | BD1: Provider Cloud ID | BE1: Provider Type | BF1: Salesforce Contact ID | BG1: Enterprise Scheduling Flag | BH1: Opt Out of Ratings | BI1: Provider Type (Substatus) ID | BJ1: Professional Suffix ID 1 | BK1: Professional Suffix ID 2 | BL1: Professional Suffix ID 3 | BM1: Specialty ID 1 | BN1: Specialty ID 2 | BO1: Specialty ID 3 | BP1: Specialty ID 4 | BQ1: Specialty ID 5 | BR1: Location ID 1 | BS1: Location ID 2 | BT1: Location ID 3 | BU1: Location ID 4 | BV1: Location ID 5 | BW1: Board Cert ID 1 | BX1: Sub Board Cert ID 1 | BY1: Board Cert ID 2 | BZ1: Sub Board Cert ID 2 | CA1: Board Cert ID 3 | CB1: Sub Board Cert ID 3 | CC1: Board Cert ID 4 | CD1: Sub Board Cert ID 4 | CE1: Board Cert ID 5 | CF1: Sub Board Cert ID 5 | CG1: Hospital Affiliation ID 1 | CH1: Hospital Affiliation ID 2 | CI1: Hospital Affiliation ID 3 | CJ1: Hospital Affiliation ID 4 | CK1: Hospital Affiliation ID 5 | CL1: Language ID 1 | CM1: Language ID 2 | CN1: Language ID 3
A2: Hosner | B2: Brittan | C2: Female | D2: APRN | G2: Midwife | H2: OB-GYN Nurse Practitioner | I2: Nurse Practitioner (OB-GYN) | L2: Both | M2: Intermountain Health UT - Central Women's Health | N2: =IFERROR(INDEX(Location!X:X, MATCH(BR2, Location!W:W, 0)), "") -> Intermountain Health UT - Central Women's Health Alta View Clinic - Women's Specialists 9450 S 1300 E Sandy UT (In Person) | O2: =IFERROR(INDEX(Location!X:X, MATCH(BS2, Location!W:W, 0)), "") -> Intermountain Health UT - Central Women's Health to be deleted -- New Harmony UT (Virtual) | P2: =IFERROR(INDEX(Location!X:X, MATCH(BT2, Location!W:W, 0)), "") | Q2: =IFERROR(INDEX(Location!X:X, MATCH(BU2, Location!W:W, 0)), "") | R2: =IFERROR(INDEX(Location!X:X, MATCH(BV2, Location!W:W, 0)), "") | S2: 1548029598 | BC2: pt_9sXRlV40j0GvSnpNVV7VRw | BE2: Practitioner - Full Profile | BG2: No | BI2: =IFERROR(INDEX(ValidationAndReference!P:P, MATCH(BE2, ValidationAndReference!Q:Q, 0)), "") -> 1 | BJ2: =IFERROR(INDEX(ValidationAndReference!F:F, MATCH(D2, ValidationAndReference!G:G, 0)), "") -> 22 | BK2: =IFERROR(INDEX(ValidationAndReference!F:F, MATCH(E2, ValidationAndReference!G:G, 0)), "") | BL2: =IFERROR(INDEX(ValidationAndReference!F:F, MATCH(F2, ValidationAndReference!G:G, 0)), "") | BM2: =IF(ISBLANK(G2),"",INDEX(ValidationAndReference!J:J,MATCH(G2,ValidationAndReference!K:K,0))) -> 362 | BN2: =IF(ISBLANK(H2),"",INDEX(ValidationAndReference!J:J,MATCH(H2,ValidationAndReference!K:K,0))) -> 404 | BO2: =IF(ISBLANK(I2),"",INDEX(ValidationAndReference!J:J,MATCH(I2,ValidationAndReference!K:K,0))) -> 523 | BP2: =IF(ISBLANK(J2),"",INDEX(ValidationAndReference!J:J,MATCH(J2,ValidationAndReference!K:K,0))) | BQ2: =IF(ISBLANK(K2),"",INDEX(ValidationAndReference!J:J,MATCH(K2,ValidationAndReference!K:K,0))) | BR2: lo_ZaDx5groBUmIgOlbOWKL-B | BS2: lo_i9HrnJ3V80i8pDnVxHIE6A | BW2: =IF(ISBLANK(AA2),"",INDEX(ValidationAndReference!$AA:$AA,MATCH(AA2,ValidationAndReference!$AB:$AB,0))) | BX2: =IF(ISBLANK(AB2),"",INDEX(ValidationAndReference!$M:$M,MATCH(AB2,ValidationAndReference!$N:$N,0))) | BY2: =IF(ISBLANK(AC2),"",INDEX(ValidationAndReference!$AA:$AA,MATCH(AC2,ValidationAndReference!$AB:$AB,0))) | BZ2: =IF(ISBLANK(AD2),"",INDEX(ValidationAndReference!$M:$M,MATCH(AD2,ValidationAndReference!$N:$N,0))) | CA2: =IF(ISBLANK(AE2),"",INDEX(ValidationAndReference!$AA:$AA,MATCH(AE2,ValidationAndReference!$AB:$AB,0))) | CB2: =IF(ISBLANK(AF2),"",INDEX(ValidationAndReference!$M:$M,MATCH(AF2,ValidationAndReference!$N:$N,0))) | CC2: =IF(ISBLANK(AG2),"",INDEX(ValidationAndReference!$AA:$AA,MATCH(AG2,ValidationAndReference!$AB:$AB,0))) | CD2: =IF(ISBLANK(AH2),"",INDEX(ValidationAndReference!$M:$M,MATCH(AH2,ValidationAndReference!$N:$N,0))) | CE2: =IF(ISBLANK(AI2),"",INDEX(ValidationAndReference!$AA:$AA,MATCH(AI2,ValidationAndReference!$AB:$AB,0))) | CF2: =IF(ISBLANK(AJ2),"",INDEX(ValidationAndReference!$M:$M,MATCH(AJ2,ValidationAndReference!$N:$N,0))) | CG2: =IF(ISBLANK(AU2),"",INDEX(ValidationAndReference!$S:$S,MATCH(AU2,ValidationAndReference!$T:$T,0))) | CH2: =IF(ISBLANK(AV2),"",INDEX(ValidationAndReference!$S:$S,MATCH(AV2,ValidationAndReference!$T:$T,0))) | CI2: =IF(ISBLANK(AW2),"",INDEX(ValidationAndReference!$S:$S,MATCH(AW2,ValidationAndReference!$T:$T,0))) | CJ2: =IF(ISBLANK(AX2),"",INDEX(ValidationAndReference!$S:$S,MATCH(AX2,ValidationAndReference!$T:$T,0))) | CK2: =IF(ISBLANK(AY2),"",INDEX(ValidationAndReference!$S:$S,MATCH(AY2,ValidationAndReference!$T:$T,0))) | CL2: =IFERROR(INDEX(ValidationAndReference!V:V, MATCH(AZ2, ValidationAndReference!W:W, 0)), "") | CM2: =IFERROR(INDEX(ValidationAndReference!V:V, MATCH(BA2, ValidationAndReference!W:W, 0)), "") | CN2: =IFERROR(INDEX(ValidationAndReference!V:V, MATCH(BB2, ValidationAndReference!W:W, 0)), "")
A3: Morris Rebecca | B3: R. | C3: Female | L3: Adult | M3: Intermountain Health UT - Central Women's Health | N3: =IFERROR(INDEX(Location!X:X, MATCH(BR3, Location!W:W, 0)), "") -> Intermountain Health UT - Central Women's Health Layton Parkway Clinic - Women's Health 201 W Layton Pkwy Ste 2B Layton UT (In Person) | O3: =IFERROR(INDEX(Location!X:X, MATCH(BS3, Location!W:W, 0)), "") | P3: =IFERROR(INDEX(Location!X:X, MATCH(BT3, Location!W:W, 0)), "") | Q3: =IFERROR(INDEX(Location!X:X, MATCH(BU3, Location!W:W, 0)), "") | R3: =IFERROR(INDEX(Location!X:X, MATCH(BV3, Location!W:W, 0)), "") | S3: 1740680926 | T3: Rebecca R. Morris, CNM - Burley, ID - Midwifery - Schedule Appointment | BC3: pt_9sXRlV40j0GvSnpNVV7VRw | BE3: Practitioner - Full Profile | BG3: No | BI3: =IFERROR(INDEX(ValidationAndReference!P:P, MATCH(BE3, ValidationAndReference!Q:Q, 0)), "") -> 1 | BJ3: =IFERROR(INDEX(ValidationAndReference!F:F, MATCH(D3, ValidationAndReference!G:G, 0)), "") | BK3: =IFERROR(INDEX(ValidationAndReference!F:F, MATCH(E3, ValidationAndReference!G:G, 0)), "") | BL3: =IFERROR(INDEX(ValidationAndReference!F:F, MATCH(F3, ValidationAndReference!G:G, 0)), "") | BM3: =IF(ISBLANK(G3),"",INDEX(ValidationAndReference!J:J,MATCH(G3,ValidationAndReference!K:K,0))) | BN3: =IF(ISBLANK(H3),"",INDEX(ValidationAndReference!J:J,MATCH(H3,ValidationAndReference!K:K,0))) | BO3: =IF(ISBLANK(I3),"",INDEX(ValidationAndReference!J:J,MATCH(I3,ValidationAndReference!K:K,0))) | BP3: =IF(ISBLANK(J3),"",INDEX(ValidationAndReference!J:J,MATCH(J3,ValidationAndReference!K:K,0))) | BQ3: =IF(ISBLANK(K3),"",INDEX(ValidationAndReference!J:J,MATCH(K3,ValidationAndReference!K:K,0))) | BR3: lo_KOSlINdfhEmmNCQ0zLZpfB | BW3: =IF(ISBLANK(AA3),"",INDEX(ValidationAndReference!$AA:$AA,MATCH(AA3,ValidationAndReference!$AB:$AB,0))) | BX3: =IF(ISBLANK(AB3),"",INDEX(ValidationAndReference!$M:$M,MATCH(AB3,ValidationAndReference!$N:$N,0))) | BY3: =IF(ISBLANK(AC3),"",INDEX(ValidationAndReference!$AA:$AA,MATCH(AC3,ValidationAndReference!$AB:$AB,0))) | BZ3: =IF(ISBLANK(AD3),"",INDEX(ValidationAndReference!$M:$M,MATCH(AD3,ValidationAndReference!$N:$N,0))) | CA3: =IF(ISBLANK(AE3),"",INDEX(ValidationAndReference!$AA:$AA,MATCH(AE3,ValidationAndReference!$AB:$AB,0))) | CB3: =IF(ISBLANK(AF3),"",INDEX(ValidationAndReference!$M:$M,MATCH(AF3,ValidationAndReference!$N:$N,0))) | CC3: =IF(ISBLANK(AG3),"",INDEX(ValidationAndReference!$AA:$AA,MATCH(AG3,ValidationAndReference!$AB:$AB,0))) | CD3: =IF(ISBLANK(AH3),"",INDEX(ValidationAndReference!$M:$M,MATCH(AH3,ValidationAndReference!$N:$N,0))) | CE3: =IF(ISBLANK(AI3),"",INDEX(ValidationAndReference!$AA:$AA,MATCH(AI3,ValidationAndReference!$AB:$AB,0))) | CF3: =IF(ISBLANK(AJ3),"",INDEX(ValidationAndReference!$M:$M,MATCH(AJ3,ValidationAndReference!$N:$N,0))) | CG3: =IF(ISBLANK(AU3),"",INDEX(ValidationAndReference!$S:$S,MATCH(AU3,ValidationAndReference!$T:$T,0))) | CH3: =IF(ISBLANK(AV3),"",INDEX(ValidationAndReference!$S:$S,MATCH(AV3,ValidationAndReference!$T:$T,0))) | CI3: =IF(ISBLANK(AW3),"",INDEX(ValidationAndReference!$S:$S,MATCH(AW3,ValidationAndReference!$T:$T,0))) | CJ3: =IF(ISBLANK(AX3),"",INDEX(ValidationAndReference!$S:$S,MATCH(AX3,ValidationAndReference!$T:$T,0))) | CK3: =IF(ISBLANK(AY3),"",INDEX(ValidationAndReference!$S:$S,MATCH(AY3,ValidationAndReference!$T:$T,0))) | CL3: =IFERROR(INDEX(ValidationAndReference!V:V, MATCH(AZ3, ValidationAndReference!W:W, 0)), "") | CM3: =IFERROR(INDEX(ValidationAndReference!V:V, MATCH(BA3, ValidationAndReference!W:W, 0)), "") | CN3: =IFERROR(INDEX(ValidationAndReference!V:V, MATCH(BB3, ValidationAndReference!W:W, 0)), "")
A4: Phillips Chelsea | B4: Chaney | C4: Female | D4: APRN | G4: Midwife | H4: OB-GYN Nurse Practitioner | I4: Nurse Practitioner (OB-GYN) | J4: Nurse Practitioner | L4: Adult | M4: Intermountain Health UT - Central Women's Health | N4: =IFERROR(INDEX(Location!X:X, MATCH(BR4, Location!W:W, 0)), "") -> Intermountain Health UT - Central Women's Health Alta View Clinic - Women's Specialists 9450 S 1300 E Sandy UT (In Person) | O4: =IFERROR(INDEX(Location!X:X, MATCH(BS4, Location!W:W, 0)), "") | P4: =IFERROR(INDEX(Location!X:X, MATCH(BT4, Location!W:W, 0)), "") | Q4: =IFERROR(INDEX(Location!X:X, MATCH(BU4, Location!W:W, 0)), "") | R4: =IFERROR(INDEX(Location!X:X, MATCH(BV4, Location!W:W, 0)), "") | S4: 1366827503 | T4: https://doctors.intermountainhealth.org/provider/chelsea-chaney-phillips/2556431 | BC4: pt_9sXRlV40j0GvSnpNVV7VRw | BE4: Practitioner - Full Profile | BG4: No | BI4: =IFERROR(INDEX(ValidationAndReference!P:P, MATCH(BE4, ValidationAndReference!Q:Q, 0)), "") -> 1 | BJ4: =IFERROR(INDEX(ValidationAndReference!F:F, MATCH(D4, ValidationAndReference!G:G, 0)), "") -> 22 | BK4: =IFERROR(INDEX(ValidationAndReference!F:F, MATCH(E4, ValidationAndReference!G:G, 0)), "") | BL4: =IFERROR(INDEX(ValidationAndReference!F:F, MATCH(F4, ValidationAndReference!G:G, 0)), "") | BM4: =IF(ISBLANK(G4),"",INDEX(ValidationAndReference!J:J,MATCH(G4,ValidationAndReference!K:K,0))) -> 362 | BN4: =IF(ISBLANK(H4),"",INDEX(ValidationAndReference!J:J,MATCH(H4,ValidationAndReference!K:K,0))) -> 404 | BO4: =IF(ISBLANK(I4),"",INDEX(ValidationAndReference!J:J,MATCH(I4,ValidationAndReference!K:K,0))) -> 523 | BP4: =IF(ISBLANK(J4),"",INDEX(ValidationAndReference!J:J,MATCH(J4,ValidationAndReference!K:K,0))) -> 399 | BQ4: =IF(ISBLANK(K4),"",INDEX(ValidationAndReference!J:J,MATCH(K4,ValidationAndReference!K:K,0))) | BR4: lo_ZaDx5groBUmIgOlbOWKL-B | BW4: =IF(ISBLANK(AA4),"",INDEX(ValidationAndReference!$AA:$AA,MATCH(AA4,ValidationAndReference!$AB:$AB,0))) | BX4: =IF(ISBLANK(AB4),"",INDEX(ValidationAndReference!$M:$M,MATCH(AB4,ValidationAndReference!$N:$N,0))) | BY4: =IF(ISBLANK(AC4),"",INDEX(ValidationAndReference!$AA:$AA,MATCH(AC4,ValidationAndReference!$AB:$AB,0))) | BZ4: =IF(ISBLANK(AD4),"",INDEX(ValidationAndReference!$M:$M,MATCH(AD4,ValidationAndReference!$N:$N,0))) | CA4: =IF(ISBLANK(AE4),"",INDEX(ValidationAndReference!$AA:$AA,MATCH(AE4,ValidationAndReference!$AB:$AB,0))) | CB4: =IF(ISBLANK(AF4),"",INDEX(ValidationAndReference!$M:$M,MATCH(AF4,ValidationAndReference!$N:$N,0))) | CC4: =IF(ISBLANK(AG4),"",INDEX(ValidationAndReference!$AA:$AA,MATCH(AG4,ValidationAndReference!$AB:$AB,0))) | CD4: =IF(ISBLANK(AH4),"",INDEX(ValidationAndReference!$M:$M,MATCH(AH4,ValidationAndReference!$N:$N,0))) | CE4: =IF(ISBLANK(AI4),"",INDEX(ValidationAndReference!$AA:$AA,MATCH(AI4,ValidationAndReference!$AB:$AB,0))) | CF4: =IF(ISBLANK(AJ4),"",INDEX(ValidationAndReference!$M:$M,MATCH(AJ4,ValidationAndReference!$N:$N,0))) | CG4: =IF(ISBLANK(AU4),"",INDEX(ValidationAndReference!$S:$S,MATCH(AU4,ValidationAndReference!$T:$T,0))) | CH4: =IF(ISBLANK(AV4),"",INDEX(ValidationAndReference!$S:$S,MATCH(AV4,ValidationAndReference!$T:$T,0))) | CI4: =IF(ISBLANK(AW4),"",INDEX(ValidationAndReference!$S:$S,MATCH(AW4,ValidationAndReference!$T:$T,0))) | CJ4: =IF(ISBLANK(AX4),"",INDEX(ValidationAndReference!$S:$S,MATCH(AX4,ValidationAndReference!$T:$T,0))) | CK4: =IF(ISBLANK(AY4),"",INDEX(ValidationAndReference!$S:$S,MATCH(AY4,ValidationAndReference!$T:$T,0))) | CL4: =IFERROR(INDEX(ValidationAndReference!V:V, MATCH(AZ4, ValidationAndReference!W:W, 0)), "") | CM4: =IFERROR(INDEX(ValidationAndReference!V:V, MATCH(BA4, ValidationAndReference!W:W, 0)), "") | CN4: =IFERROR(INDEX(ValidationAndReference!V:V, MATCH(BB4, ValidationAndReference!W:W, 0)), "")
A5: Stanger | B5: Cynthia | C5: Female | D5: CNM | G5: Midwife | H5: OB-GYN Nurse Practitioner | I5: Nurse Practitioner (OB-GYN) | L5: Adult | M5: Intermountain Health UT - Central Women's Health | N5: =IFERROR(INDEX(Location!X:X, MATCH(BR5, Location!W:W, 0)), "") -> Intermountain Health UT - Central Women's Health Avenues Women's Center 370 E 9th Ave Ste 205 Salt Lake City UT (In Person) | O5: =IFERROR(INDEX(Location!X:X, MATCH(BS5, Location!W:W, 0)), "") -> Intermountain Health UT - Central Women's Health Bountiful Clinic - Women'S Health 390 N Main St Bountiful UT (In Person) | P5: =IFERROR(INDEX(Location!X:X, MATCH(BT5, Location!W:W, 0)), "") | Q5: =IFERROR(INDEX(Location!X:X, MATCH(BU5, Location!W:W, 0)), "") | R5: =IFERROR(INDEX(Location!X:X, MATCH(BV5, Location!W:W, 0)), "") | S5: 1447552955 | T5: https://doctors.intermountainhealth.org/provider/cynthia-stanger/2557184 | AZ5: Spanish | BC5: pt_9sXRlV40j0GvSnpNVV7VRw | BE5: Practitioner - Full Profile | BG5: No | BI5: =IFERROR(INDEX(ValidationAndReference!P:P, MATCH(BE5, ValidationAndReference!Q:Q, 0)), "") -> 1 | BJ5: =IFERROR(INDEX(ValidationAndReference!F:F, MATCH(D5, ValidationAndReference!G:G, 0)), "") -> 40 | BK5: =IFERROR(INDEX(ValidationAndReference!F:F, MATCH(E5, ValidationAndReference!G:G, 0)), "") | BL5: =IFERROR(INDEX(ValidationAndReference!F:F, MATCH(F5, ValidationAndReference!G:G, 0)), "") | BM5: =IF(ISBLANK(G5),"",INDEX(ValidationAndReference!J:J,MATCH(G5,ValidationAndReference!K:K,0))) -> 362 | BN5: =IF(ISBLANK(H5),"",INDEX(ValidationAndReference!J:J,MATCH(H5,ValidationAndReference!K:K,0))) -> 404 | BO5: =IF(ISBLANK(I5),"",INDEX(ValidationAndReference!J:J,MATCH(I5,ValidationAndReference!K:K,0))) -> 523 | BP5: =IF(ISBLANK(J5),"",INDEX(ValidationAndReference!J:J,MATCH(J5,ValidationAndReference!K:K,0))) | BQ5: =IF(ISBLANK(K5),"",INDEX(ValidationAndReference!J:J,MATCH(K5,ValidationAndReference!K:K,0))) | BR5: lo_0P-S0R44AEypsKxmG4cTjR | BS5: lo_2ly69_fZ50GORUzOt38fqR | BW5: =IF(ISBLANK(AA5),"",INDEX(ValidationAndReference!$AA:$AA,MATCH(AA5,ValidationAndReference!$AB:$AB,0))) | BX5: =IF(ISBLANK(AB5),"",INDEX(ValidationAndReference!$M:$M,MATCH(AB5,ValidationAndReference!$N:$N,0))) | BY5: =IF(ISBLANK(AC5),"",INDEX(ValidationAndReference!$AA:$AA,MATCH(AC5,ValidationAndReference!$AB:$AB,0))) | BZ5: =IF(ISBLANK(AD5),"",INDEX(ValidationAndReference!$M:$M,MATCH(AD5,ValidationAndReference!$N:$N,0))) | CA5: =IF(ISBLANK(AE5),"",INDEX(ValidationAndReference!$AA:$AA,MATCH(AE5,ValidationAndReference!$AB:$AB,0))) | CB5: =IF(ISBLANK(AF5),"",INDEX(ValidationAndReference!$M:$M,MATCH(AF5,ValidationAndReference!$N:$N,0))) | CC5: =IF(ISBLANK(AG5),"",INDEX(ValidationAndReference!$AA:$AA,MATCH(AG5,ValidationAndReference!$AB:$AB,0))) | CD5: =IF(ISBLANK(AH5),"",INDEX(ValidationAndReference!$M:$M,MATCH(AH5,ValidationAndReference!$N:$N,0))) | CE5: =IF(ISBLANK(AI5),"",INDEX(ValidationAndReference!$AA:$AA,MATCH(AI5,ValidationAndReference!$AB:$AB,0))) | CF5: =IF(ISBLANK(AJ5),"",INDEX(ValidationAndReference!$M:$M,MATCH(AJ5,ValidationAndReference!$N:$N,0))) | CG5: =IF(ISBLANK(AU5),"",INDEX(ValidationAndReference!$S:$S,MATCH(AU5,ValidationAndReference!$T:$T,0))) | CH5: =IF(ISBLANK(AV5),"",INDEX(ValidationAndReference!$S:$S,MATCH(AV5,ValidationAndReference!$T:$T,0))) | CI5: =IF(ISBLANK(AW5),"",INDEX(ValidationAndReference!$S:$S,MATCH(AW5,ValidationAndReference!$T:$T,0))) | CJ5: =IF(ISBLANK(AX5),"",INDEX(ValidationAndReference!$S:$S,MATCH(AX5,ValidationAndReference!$T:$T,0))) | CK5: =IF(ISBLANK(AY5),"",INDEX(ValidationAndReference!$S:$S,MATCH(AY5,ValidationAndReference!$T:$T,0))) | CL5: =IFERROR(INDEX(ValidationAndReference!V:V, MATCH(AZ5, ValidationAndReference!W:W, 0)), "") -> 3 | CM5: =IFERROR(INDEX(ValidationAndReference!V:V, MATCH(BA5, ValidationAndReference!W:W, 0)), "") | CN5: =IFERROR(INDEX(ValidationAndReference!V:V, MATCH(BB5, ValidationAndReference!W:W, 0)), "")
A6: Yearsley Carlie | B6: A. | C6: Female | D6: APRN | G6: Midwife | H6: OB-GYN Nurse Practitioner | I6: Nurse Practitioner (OB-GYN) | L6: Adult | M6: Intermountain Health UT - Central Women's Health | N6: =IFERROR(INDEX(Location!X:X, MATCH(BR6, Location!W:W, 0)), "") -> Intermountain Health UT - Central Women's Health Alta View Clinic - Women's Specialists 9450 S 1300 E Sandy UT (In Person) | O6: =IFERROR(INDEX(Location!X:X, MATCH(BS6, Location!W:W, 0)), "") | P6: =IFERROR(INDEX(Location!X:X, MATCH(BT6, Location!W:W, 0)), "") | Q6: =IFERROR(INDEX(Location!X:X, MATCH(BU6, Location!W:W, 0)), "") | R6: =IFERROR(INDEX(Location!X:X, MATCH(BV6, Location!W:W, 0)), "") | S6: 1215285614 | T6: https://doctors.intermountainhealth.org/provider/carlie-a-yearsley/2556636 | BC6: pt_9sXRlV40j0GvSnpNVV7VRw | BE6: Practitioner - Full Profile | BG6: No | BI6: =IFERROR(INDEX(ValidationAndReference!P:P, MATCH(BE6, ValidationAndReference!Q:Q, 0)), "") -> 1 | BJ6: =IFERROR(INDEX(ValidationAndReference!F:F, MATCH(D6, ValidationAndReference!G:G, 0)), "") -> 22 | BK6: =IFERROR(INDEX(ValidationAndReference!F:F, MATCH(E6, ValidationAndReference!G:G, 0)), "") | BL6: =IFERROR(INDEX(ValidationAndReference!F:F, MATCH(F6, ValidationAndReference!G:G, 0)), "") | BM6: =IF(ISBLANK(G6),"",INDEX(ValidationAndReference!J:J,MATCH(G6,ValidationAndReference!K:K,0))) -> 362 | BN6: =IF(ISBLANK(H6),"",INDEX(ValidationAndReference!J:J,MATCH(H6,ValidationAndReference!K:K,0))) -> 404 | BO6: =IF(ISBLANK(I6),"",INDEX(ValidationAndReference!J:J,MATCH(I6,ValidationAndReference!K:K,0))) -> 523 | BP6: =IF(ISBLANK(J6),"",INDEX(ValidationAndReference!J:J,MATCH(J6,ValidationAndReference!K:K,0))) | BQ6: =IF(ISBLANK(K6),"",INDEX(ValidationAndReference!J:J,MATCH(K6,ValidationAndReference!K:K,0))) | BR6: lo_ZaDx5groBUmIgOlbOWKL-B | BW6: =IF(ISBLANK(AA6),"",INDEX(ValidationAndReference!$AA:$AA,MATCH(AA6,ValidationAndReference!$AB:$AB,0))) | BX6: =IF(ISBLANK(AB6),"",INDEX(ValidationAndReference!$M:$M,MATCH(AB6,ValidationAndReference!$N:$N,0))) | BY6: =IF(ISBLANK(AC6),"",INDEX(ValidationAndReference!$AA:$AA,MATCH(AC6,ValidationAndReference!$AB:$AB,0))) | BZ6: =IF(ISBLANK(AD6),"",INDEX(ValidationAndReference!$M:$M,MATCH(AD6,ValidationAndReference!$N:$N,0))) | CA6: =IF(ISBLANK(AE6),"",INDEX(ValidationAndReference!$AA:$AA,MATCH(AE6,ValidationAndReference!$AB:$AB,0))) | CB6: =IF(ISBLANK(AF6),"",INDEX(ValidationAndReference!$M:$M,MATCH(AF6,ValidationAndReference!$N:$N,0))) | CC6: =IF(ISBLANK(AG6),"",INDEX(ValidationAndReference!$AA:$AA,MATCH(AG6,ValidationAndReference!$AB:$AB,0))) | CD6: =IF(ISBLANK(AH6),"",INDEX(ValidationAndReference!$M:$M,MATCH(AH6,ValidationAndReference!$N:$N,0))) | CE6: =IF(ISBLANK(AI6),"",INDEX(ValidationAndReference!$AA:$AA,MATCH(AI6,ValidationAndReference!$AB:$AB,0))) | CF6: =IF(ISBLANK(AJ6),"",INDEX(ValidationAndReference!$M:$M,MATCH(AJ6,ValidationAndReference!$N:$N,0))) | CG6: =IF(ISBLANK(AU6),"",INDEX(ValidationAndReference!$S:$S,MATCH(AU6,ValidationAndReference!$T:$T,0))) | CH6: =IF(ISBLANK(AV6),"",INDEX(ValidationAndReference!$S:$S,MATCH(AV6,ValidationAndReference!$T:$T,0))) | CI6: =IF(ISBLANK(AW6),"",INDEX(ValidationAndReference!$S:$S,MATCH(AW6,ValidationAndReference!$T:$T,0))) | CJ6: =IF(ISBLANK(AX6),"",INDEX(ValidationAndReference!$S:$S,MATCH(AX6,ValidationAndReference!$T:$T,0))) | CK6: =IF(ISBLANK(AY6),"",INDEX(ValidationAndReference!$S:$S,MATCH(AY6,ValidationAndReference!$T:$T,0))) | CL6: =IFERROR(INDEX(ValidationAndReference!V:V, MATCH(AZ6, ValidationAndReference!W:W, 0)), "") | CM6: =IFERROR(INDEX(ValidationAndReference!V:V, MATCH(BA6, ValidationAndReference!W:W, 0)), "") | CN6: =IFERROR(INDEX(ValidationAndReference!V:V, MATCH(BB6, ValidationAndReference!W:W, 0)), "")
A7: Bearnson Camra | B7: J. | C7: Female | D7: APRN | G7: Midwife | H7: OB-GYN Nurse Practitioner | I7: Nurse Practitioner (OB-GYN) | L7: Adult | N7: =IFERROR(INDEX(Location!X:X, MATCH(BR7, Location!W:W, 0)), "") | O7: =IFERROR(INDEX(Location!X:X, MATCH(BS7, Location!W:W, 0)), "") | P7: =IFERROR(INDEX(Location!X:X, MATCH(BT7, Location!W:W, 0)), "") | Q7: =IFERROR(INDEX(Location!X:X, MATCH(BU7, Location!W:W, 0)), "") | R7: =IFERROR(INDEX(Location!X:X, MATCH(BV7, Location!W:W, 0)), "") | S7: 1336654334 | T7: https://doctors.intermountainhealth.org/provider/camra-j-bearnson/2560083 | BE7: Practitioner - Full Profile | BG7: No | BI7: =IFERROR(INDEX(ValidationAndReference!P:P, MATCH(BE7, ValidationAndReference!Q:Q, 0)), "") -> 1 | BJ7: =IFERROR(INDEX(ValidationAndReference!F:F, MATCH(D7, ValidationAndReference!G:G, 0)), "") -> 22 | BK7: =IFERROR(INDEX(ValidationAndReference!F:F, MATCH(E7, ValidationAndReference!G:G, 0)), "") | BL7: =IFERROR(INDEX(ValidationAndReference!F:F, MATCH(F7, ValidationAndReference!G:G, 0)), "") | BM7: =IF(ISBLANK(G7),"",INDEX(ValidationAndReference!J:J,MATCH(G7,ValidationAndReference!K:K,0))) -> 362 | BN7: =IF(ISBLANK(H7),"",INDEX(ValidationAndReference!J:J,MATCH(H7,ValidationAndReference!K:K,0))) -> 404 | BO7: =IF(ISBLANK(I7),"",INDEX(ValidationAndReference!J:J,MATCH(I7,ValidationAndReference!K:K,0))) -> 523 | BP7: =IF(ISBLANK(J7),"",INDEX(ValidationAndReference!J:J,MATCH(J7,ValidationAndReference!K:K,0))) | BQ7: =IF(ISBLANK(K7),"",INDEX(ValidationAndReference!J:J,MATCH(K7,ValidationAndReference!K:K,0))) | BW7: =IF(ISBLANK(AA7),"",INDEX(ValidationAndReference!$AA:$AA,MATCH(AA7,ValidationAndReference!$AB:$AB,0))) | BX7: =IF(ISBLANK(AB7),"",INDEX(ValidationAndReference!$M:$M,MATCH(AB7,ValidationAndReference!$N:$N,0))) | BY7: =IF(ISBLANK(AC7),"",INDEX(ValidationAndReference!$AA:$AA,MATCH(AC7,ValidationAndReference!$AB:$AB,0))) | BZ7: =IF(ISBLANK(AD7),"",INDEX(ValidationAndReference!$M:$M,MATCH(AD7,ValidationAndReference!$N:$N,0))) | CA7: =IF(ISBLANK(AE7),"",INDEX(ValidationAndReference!$AA:$AA,MATCH(AE7,ValidationAndReference!$AB:$AB,0))) | CB7: =IF(ISBLANK(AF7),"",INDEX(ValidationAndReference!$M:$M,MATCH(AF7,ValidationAndReference!$N:$N,0))) | CC7: =IF(ISBLANK(AG7),"",INDEX(ValidationAndReference!$AA:$AA,MATCH(AG7,ValidationAndReference!$AB:$AB,0))) | CD7: =IF(ISBLANK(AH7),"",INDEX(ValidationAndReference!$M:$M,MATCH(AH7,ValidationAndReference!$N:$N,0))) | CE7: =IF(ISBLANK(AI7),"",INDEX(ValidationAndReference!$AA:$AA,MATCH(AI7,ValidationAndReference!$AB:$AB,0))) | CF7: =IF(ISBLANK(AJ7),"",INDEX(ValidationAndReference!$M:$M,MATCH(AJ7,ValidationAndReference!$N:$N,0))) | CG7: =IF(ISBLANK(AU7),"",INDEX(ValidationAndReference!$S:$S,MATCH(AU7,ValidationAndReference!$T:$T,0))) | CH7: =IF(ISBLANK(AV7),"",INDEX(ValidationAndReference!$S:$S,MATCH(AV7,ValidationAndReference!$T:$T,0))) | CI7: =IF(ISBLANK(AW7),"",INDEX(ValidationAndReference!$S:$S,MATCH(AW7,ValidationAndReference!$T:$T,0))) | CJ7: =IF(ISBLANK(AX7),"",INDEX(ValidationAndReference!$S:$S,MATCH(AX7,ValidationAndReference!$T:$T,0))) | CK7: =IF(ISBLANK(AY7),"",INDEX(ValidationAndReference!$S:$S,MATCH(AY7,ValidationAndReference!$T:$T,0))) | CL7: =IFERROR(INDEX(ValidationAndReference!V:V, MATCH(AZ7, ValidationAndReference!W:W, 0)), "") | CM7: =IFERROR(INDEX(ValidationAndReference!V:V, MATCH(BA7, ValidationAndReference!W:W, 0)), "") | CN7: =IFERROR(INDEX(ValidationAndReference!V:V, MATCH(BB7, ValidationAndReference!W:W, 0)), "")
A8: Black Kristen | B8: H. | C8: Female | D8: DO | G8: OB-GYN | L8: Adult | M8: Intermountain Health UT - Central Women's Health | N8: =IFERROR(INDEX(Location!X:X, MATCH(BR8, Location!W:W, 0)), "") -> Intermountain Health UT - Central Women's Health Southridge Clinic - OB/Gyn 3723 W 12600 S Ste 360 Riverton UT (In Person) | O8: =IFERROR(INDEX(Location!X:X, MATCH(BS8, Location!W:W, 0)), "") -> Intermountain Health UT - Central Women's Health to be deleted -- New Harmony UT (Virtual) | P8: =IFERROR(INDEX(Location!X:X, MATCH(BT8, Location!W:W, 0)), "") | Q8: =IFERROR(INDEX(Location!X:X, MATCH(BU8, Location!W:W, 0)), "") | R8: =IFERROR(INDEX(Location!X:X, MATCH(BV8, Location!W:W, 0)), "") | S8: 1982965034 | T8: https://doctors.intermountainhealth.org/provider/kristen-h-black/2556508 | BC8: pt_9sXRlV40j0GvSnpNVV7VRw | BE8: Practitioner - Full Profile | BG8: No | BI8: =IFERROR(INDEX(ValidationAndReference!P:P, MATCH(BE8, ValidationAndReference!Q:Q, 0)), "") -> 1 | BJ8: =IFERROR(INDEX(ValidationAndReference!F:F, MATCH(D8, ValidationAndReference!G:G, 0)), "") -> 4 | BK8: =IFERROR(INDEX(ValidationAndReference!F:F, MATCH(E8, ValidationAndReference!G:G, 0)), "") | BL8: =IFERROR(INDEX(ValidationAndReference!F:F, MATCH(F8, ValidationAndReference!G:G, 0)), "") | BM8: =IF(ISBLANK(G8),"",INDEX(ValidationAndReference!J:J,MATCH(G8,ValidationAndReference!K:K,0))) -> 104 | BN8: =IF(ISBLANK(H8),"",INDEX(ValidationAndReference!J:J,MATCH(H8,ValidationAndReference!K:K,0))) | BO8: =IF(ISBLANK(I8),"",INDEX(ValidationAndReference!J:J,MATCH(I8,ValidationAndReference!K:K,0))) | BP8: =IF(ISBLANK(J8),"",INDEX(ValidationAndReference!J:J,MATCH(J8,ValidationAndReference!K:K,0))) | BQ8: =IF(ISBLANK(K8),"",INDEX(ValidationAndReference!J:J,MATCH(K8,ValidationAndReference!K:K,0))) | BR8: lo_YWHkLUhm8EOqqaiT6WcOnh | BS8: lo_i9HrnJ3V80i8pDnVxHIE6A | BW8: =IF(ISBLANK(AA8),"",INDEX(ValidationAndReference!$AA:$AA,MATCH(AA8,ValidationAndReference!$AB:$AB,0))) | BX8: =IF(ISBLANK(AB8),"",INDEX(ValidationAndReference!$M:$M,MATCH(AB8,ValidationAndReference!$N:$N,0))) | BY8: =IF(ISBLANK(AC8),"",INDEX(ValidationAndReference!$AA:$AA,MATCH(AC8,ValidationAndReference!$AB:$AB,0))) | BZ8: =IF(ISBLANK(AD8),"",INDEX(ValidationAndReference!$M:$M,MATCH(AD8,ValidationAndReference!$N:$N,0))) | CA8: =IF(ISBLANK(AE8),"",INDEX(ValidationAndReference!$AA:$AA,MATCH(AE8,ValidationAndReference!$AB:$AB,0))) | CB8: =IF(ISBLANK(AF8),"",INDEX(ValidationAndReference!$M:$M,MATCH(AF8,ValidationAndReference!$N:$N,0))) | CC8: =IF(ISBLANK(AG8),"",INDEX(ValidationAndReference!$AA:$AA,MATCH(AG8,ValidationAndReference!$AB:$AB,0))) | CD8: =IF(ISBLANK(AH8),"",INDEX(ValidationAndReference!$M:$M,MATCH(AH8,ValidationAndReference!$N:$N,0))) | CE8: =IF(ISBLANK(AI8),"",INDEX(ValidationAndReference!$AA:$AA,MATCH(AI8,ValidationAndReference!$AB:$AB,0))) | CF8: =IF(ISBLANK(AJ8),"",INDEX(ValidationAndReference!$M:$M,MATCH(AJ8,ValidationAndReference!$N:$N,0))) | CG8: =IF(ISBLANK(AU8),"",INDEX(ValidationAndReference!$S:$S,MATCH(AU8,ValidationAndReference!$T:$T,0))) | CH8: =IF(ISBLANK(AV8),"",INDEX(ValidationAndReference!$S:$S,MATCH(AV8,ValidationAndReference!$T:$T,0))) | CI8: =IF(ISBLANK(AW8),"",INDEX(ValidationAndReference!$S:$S,MATCH(AW8,ValidationAndReference!$T:$T,0))) | CJ8: =IF(ISBLANK(AX8),"",INDEX(ValidationAndReference!$S:$S,MATCH(AX8,ValidationAndReference!$T:$T,0))) | CK8: =IF(ISBLANK(AY8),"",INDEX(ValidationAndReference!$S:$S,MATCH(AY8,ValidationAndReference!$T:$T,0))) | CL8: =IFERROR(INDEX(ValidationAndReference!V:V, MATCH(AZ8, ValidationAndReference!W:W, 0)), "") | CM8: =IFERROR(INDEX(ValidationAndReference!V:V, MATCH(BA8, ValidationAndReference!W:W, 0)), "") | CN8: =IFERROR(INDEX(ValidationAndReference!V:V, MATCH(BB8, ValidationAndReference!W:W, 0)), "")
A9: Bowman Jane | B9: C. | C9: Female | D9: MD | G9: OB-GYN | L9: Adult | M9: Intermountain Health UT - Central Women's Health | N9: =IFERROR(INDEX(Location!X:X, MATCH(BR9, Location!W:W, 0)), "") -> Intermountain Health UT - Central Women's Health Southridge Clinic - OB/Gyn 3723 W 12600 S Ste 360 Riverton UT (In Person) | O9: =IFERROR(INDEX(Location!X:X, MATCH(BS9, Location!W:W, 0)), "") -> Intermountain Health UT - Central Women's Health to be deleted -- New Harmony UT (Virtual) | P9: =IFERROR(INDEX(Location!X:X, MATCH(BT9, Location!W:W, 0)), "") | Q9: =IFERROR(INDEX(Location!X:X, MATCH(BU9, Location!W:W, 0)), "") | R9: =IFERROR(INDEX(Location!X:X, MATCH(BV9, Location!W:W, 0)), "") | S9: 1073621611 | T9: https://doctors.intermountainhealth.org/provider/jane-c-bowman/2561271 | BC9: pt_9sXRlV40j0GvSnpNVV7VRw | BE9: Practitioner - Full Profile | BG9: No | BI9: =IFERROR(INDEX(ValidationAndReference!P:P, MATCH(BE9, ValidationAndReference!Q:Q, 0)), "") -> 1 | BJ9: =IFERROR(INDEX(ValidationAndReference!F:F, MATCH(D9, ValidationAndReference!G:G, 0)), "") -> 1 | BK9: =IFERROR(INDEX(ValidationAndReference!F:F, MATCH(E9, ValidationAndReference!G:G, 0)), "") | BL9: =IFERROR(INDEX(ValidationAndReference!F:F, MATCH(F9, ValidationAndReference!G:G, 0)), "") | BM9: =IF(ISBLANK(G9),"",INDEX(ValidationAndReference!J:J,MATCH(G9,ValidationAndReference!K:K,0))) -> 104 | BN9: =IF(ISBLANK(H9),"",INDEX(ValidationAndReference!J:J,MATCH(H9,ValidationAndReference!K:K,0))) | BO9: =IF(ISBLANK(I9),"",INDEX(ValidationAndReference!J:J,MATCH(I9,ValidationAndReference!K:K,0))) | BP9: =IF(ISBLANK(J9),"",INDEX(ValidationAndReference!J:J,MATCH(J9,ValidationAndReference!K:K,0))) | BQ9: =IF(ISBLANK(K9),"",INDEX(ValidationAndReference!J:J,MATCH(K9,ValidationAndReference!K:K,0))) | BR9: lo_YWHkLUhm8EOqqaiT6WcOnh | BS9: lo_i9HrnJ3V80i8pDnVxHIE6A | BW9: =IF(ISBLANK(AA9),"",INDEX(ValidationAndReference!$AA:$AA,MATCH(AA9,ValidationAndReference!$AB:$AB,0))) | BX9: =IF(ISBLANK(AB9),"",INDEX(ValidationAndReference!$M:$M,MATCH(AB9,ValidationAndReference!$N:$N,0))) | BY9: =IF(ISBLANK(AC9),"",INDEX(ValidationAndReference!$AA:$AA,MATCH(AC9,ValidationAndReference!$AB:$AB,0))) | BZ9: =IF(ISBLANK(AD9),"",INDEX(ValidationAndReference!$M:$M,MATCH(AD9,ValidationAndReference!$N:$N,0))) | CA9: =IF(ISBLANK(AE9),"",INDEX(ValidationAndReference!$AA:$AA,MATCH(AE9,ValidationAndReference!$AB:$AB,0))) | CB9: =IF(ISBLANK(AF9),"",INDEX(ValidationAndReference!$M:$M,MATCH(AF9,ValidationAndReference!$N:$N,0))) | CC9: =IF(ISBLANK(AG9),"",INDEX(ValidationAndReference!$AA:$AA,MATCH(AG9,ValidationAndReference!$AB:$AB,0))) | CD9: =IF(ISBLANK(AH9),"",INDEX(ValidationAndReference!$M:$M,MATCH(AH9,ValidationAndReference!$N:$N,0))) | CE9: =IF(ISBLANK(AI9),"",INDEX(ValidationAndReference!$AA:$AA,MATCH(AI9,ValidationAndReference!$AB:$AB,0))) | CF9: =IF(ISBLANK(AJ9),"",INDEX(ValidationAndReference!$M:$M,MATCH(AJ9,ValidationAndReference!$N:$N,0))) | CG9: =IF(ISBLANK(AU9),"",INDEX(ValidationAndReference!$S:$S,MATCH(AU9,ValidationAndReference!$T:$T,0))) | CH9: =IF(ISBLANK(AV9),"",INDEX(ValidationAndReference!$S:$S,MATCH(AV9,ValidationAndReference!$T:$T,0))) | CI9: =IF(ISBLANK(AW9),"",INDEX(ValidationAndReference!$S:$S,MATCH(AW9,ValidationAndReference!$T:$T,0))) | CJ9: =IF(ISBLANK(AX9),"",INDEX(ValidationAndReference!$S:$S,MATCH(AX9,ValidationAndReference!$T:$T,0))) | CK9: =IF(ISBLANK(AY9),"",INDEX(ValidationAndReference!$S:$S,MATCH(AY9,ValidationAndReference!$T:$T,0))) | CL9: =IFERROR(INDEX(ValidationAndReference!V:V, MATCH(AZ9, ValidationAndReference!W:W, 0)), "") | CM9: =IFERROR(INDEX(ValidationAndReference!V:V, MATCH(BA9, ValidationAndReference!W:W, 0)), "") | CN9: =IFERROR(INDEX(ValidationAndReference!V:V, MATCH(BB9, ValidationAndReference!W:W, 0)), "")
A10: Brown Melissa | B10: Ann | C10: Female | D10: MD | G10: OB-GYN | L10: Adult | M10: Intermountain Health UT - Central Women's Health | N10: =IFERROR(INDEX(Location!X:X, MATCH(BR10, Location!W:W, 0)), "") -> Intermountain Health UT - Central Women's Health Obstetrics & Gynecology Specialists 5063 S Cottonwood St Ste 120 Murray UT (In Person) | O10: =IFERROR(INDEX(Location!X:X, MATCH(BS10, Location!W:W, 0)), "") -> Intermountain Health UT - Central Women's Health to be deleted -- New Harmony UT (Virtual) | P10: =IFERROR(INDEX(Location!X:X, MATCH(BT10, Location!W:W, 0)), "") | Q10: =IFERROR(INDEX(Location!X:X, MATCH(BU10, Location!W:W, 0)), "") | R10: =IFERROR(INDEX(Location!X:X, MATCH(BV10, Location!W:W, 0)), "") | S10: 1508881210 | T10: https://doctors.intermountainhealth.org/provider/melissa-ann-brown/2559416 | BC10: pt_9sXRlV40j0GvSnpNVV7VRw | BE10: Practitioner - Full Profile | BG10: No | BI10: =IFERROR(INDEX(ValidationAndReference!P:P, MATCH(BE10, ValidationAndReference!Q:Q, 0)), "") -> 1 | BJ10: =IFERROR(INDEX(ValidationAndReference!F:F, MATCH(D10, ValidationAndReference!G:G, 0)), "") -> 1 | BK10: =IFERROR(INDEX(ValidationAndReference!F:F, MATCH(E10, ValidationAndReference!G:G, 0)), "") | BL10: =IFERROR(INDEX(ValidationAndReference!F:F, MATCH(F10, ValidationAndReference!G:G, 0)), "") | BM10: =IF(ISBLANK(G10),"",INDEX(ValidationAndReference!J:J,MATCH(G10,ValidationAndReference!K:K,0))) -> 104 | BN10: =IF(ISBLANK(H10),"",INDEX(ValidationAndReference!J:J,MATCH(H10,ValidationAndReference!K:K,0))) | BO10: =IF(ISBLANK(I10),"",INDEX(ValidationAndReference!J:J,MATCH(I10,ValidationAndReference!K:K,0))) | BP10: =IF(ISBLANK(J10),"",INDEX(ValidationAndReference!J:J,MATCH(J10,ValidationAndReference!K:K,0))) | BQ10: =IF(ISBLANK(K10),"",INDEX(ValidationAndReference!J:J,MATCH(K10,ValidationAndReference!K:K,0))) | BR10: lo_lPottpvJyEqiYFdt6pcgbh | BS10: lo_i9HrnJ3V80i8pDnVxHIE6A | BW10: =IF(ISBLANK(AA10),"",INDEX(ValidationAndReference!$AA:$AA,MATCH(AA10,ValidationAndReference!$AB:$AB,0))) | BX10: =IF(ISBLANK(AB10),"",INDEX(ValidationAndReference!$M:$M,MATCH(AB10,ValidationAndReference!$N:$N,0))) | BY10: =IF(ISBLANK(AC10),"",INDEX(ValidationAndReference!$AA:$AA,MATCH(AC10,ValidationAndReference!$AB:$AB,0))) | BZ10: =IF(ISBLANK(AD10),"",INDEX(ValidationAndReference!$M:$M,MATCH(AD10,ValidationAndReference!$N:$N,0))) | CA10: =IF(ISBLANK(AE10),"",INDEX(ValidationAndReference!$AA:$AA,MATCH(AE10,ValidationAndReference!$AB:$AB,0))) | CB10: =IF(ISBLANK(AF10),"",INDEX(ValidationAndReference!$M:$M,MATCH(AF10,ValidationAndReference!$N:$N,0))) | CC10: =IF(ISBLANK(AG10),"",INDEX(ValidationAndReference!$AA:$AA,MATCH(AG10,ValidationAndReference!$AB:$AB,0))) | CD10: =IF(ISBLANK(AH10),"",INDEX(ValidationAndReference!$M:$M,MATCH(AH10,ValidationAndReference!$N:$N,0))) | CE10: =IF(ISBLANK(AI10),"",INDEX(ValidationAndReference!$AA:$AA,MATCH(AI10,ValidationAndReference!$AB:$AB,0))) | CF10: =IF(ISBLANK(AJ10),"",INDEX(ValidationAndReference!$M:$M,MATCH(AJ10,ValidationAndReference!$N:$N,0))) | CG10: =IF(ISBLANK(AU10),"",INDEX(ValidationAndReference!$S:$S,MATCH(AU10,ValidationAndReference!$T:$T,0))) | CH10: =IF(ISBLANK(AV10),"",INDEX(ValidationAndReference!$S:$S,MATCH(AV10,ValidationAndReference!$T:$T,0))) | CI10: =IF(ISBLANK(AW10),"",INDEX(ValidationAndReference!$S:$S,MATCH(AW10,ValidationAndReference!$T:$T,0))) | CJ10: =IF(ISBLANK(AX10),"",INDEX(ValidationAndReference!$S:$S,MATCH(AX10,ValidationAndReference!$T:$T,0))) | CK10: =IF(ISBLANK(AY10),"",INDEX(ValidationAndReference!$S:$S,MATCH(AY10,ValidationAndReference!$T:$T,0))) | CL10: =IFERROR(INDEX(ValidationAndReference!V:V, MATCH(AZ10, ValidationAndReference!W:W, 0)), "") | CM10: =IFERROR(INDEX(ValidationAndReference!V:V, MATCH(BA10, ValidationAndReference!W:W, 0)), "") | CN10: =IFERROR(INDEX(ValidationAndReference!V:V, MATCH(BB10, ValidationAndReference!W:W, 0)), "")
A11: Clark Chad | B11: Jeremy | C11: Male | D11: DO | G11: OB-GYN | H11: Family Physician | I11: Primary Care Doctor | L11: Adult | N11: =IFERROR(INDEX(Location!X:X, MATCH(BR11, Location!W:W, 0)), "") | O11: =IFERROR(INDEX(Location!X:X, MATCH(BS11, Location!W:W, 0)), "") | P11: =IFERROR(INDEX(Location!X:X, MATCH(BT11, Location!W:W, 0)), "") | Q11: =IFERROR(INDEX(Location!X:X, MATCH(BU11, Location!W:W, 0)), "") | R11: =IFERROR(INDEX(Location!X:X, MATCH(BV11, Location!W:W, 0)), "") | S11: 1346339496 | T11: https://doctors.intermountainhealth.org/provider/c-jeremy-clark/2560818 | BE11: Practitioner - Full Profile | BG11: No | BI11: =IFERROR(INDEX(ValidationAndReference!P:P, MATCH(BE11, ValidationAndReference!Q:Q, 0)), "") -> 1 | BJ11: =IFERROR(INDEX(ValidationAndReference!F:F, MATCH(D11, ValidationAndReference!G:G, 0)), "") -> 4 | BK11: =IFERROR(INDEX(ValidationAndReference!F:F, MATCH(E11, ValidationAndReference!G:G, 0)), "") | BL11: =IFERROR(INDEX(ValidationAndReference!F:F, MATCH(F11, ValidationAndReference!G:G, 0)), "") | BM11: =IF(ISBLANK(G11),"",INDEX(ValidationAndReference!J:J,MATCH(G11,ValidationAndReference!K:K,0))) -> 104 | BN11: =IF(ISBLANK(H11),"",INDEX(ValidationAndReference!J:J,MATCH(H11,ValidationAndReference!K:K,0))) -> 102 | BO11: =IF(ISBLANK(I11),"",INDEX(ValidationAndReference!J:J,MATCH(I11,ValidationAndReference!K:K,0))) -> 153 | BP11: =IF(ISBLANK(J11),"",INDEX(ValidationAndReference!J:J,MATCH(J11,ValidationAndReference!K:K,0))) | BQ11: =IF(ISBLANK(K11),"",INDEX(ValidationAndReference!J:J,MATCH(K11,ValidationAndReference!K:K,0))) | BW11: =IF(ISBLANK(AA11),"",INDEX(ValidationAndReference!$AA:$AA,MATCH(AA11,ValidationAndReference!$AB:$AB,0))) | BX11: =IF(ISBLANK(AB11),"",INDEX(ValidationAndReference!$M:$M,MATCH(AB11,ValidationAndReference!$N:$N,0))) | BY11: =IF(ISBLANK(AC11),"",INDEX(ValidationAndReference!$AA:$AA,MATCH(AC11,ValidationAndReference!$AB:$AB,0))) | BZ11: =IF(ISBLANK(AD11),"",INDEX(ValidationAndReference!$M:$M,MATCH(AD11,ValidationAndReference!$N:$N,0))) | CA11: =IF(ISBLANK(AE11),"",INDEX(ValidationAndReference!$AA:$AA,MATCH(AE11,ValidationAndReference!$AB:$AB,0))) | CB11: =IF(ISBLANK(AF11),"",INDEX(ValidationAndReference!$M:$M,MATCH(AF11,ValidationAndReference!$N:$N,0))) | CC11: =IF(ISBLANK(AG11),"",INDEX(ValidationAndReference!$AA:$AA,MATCH(AG11,ValidationAndReference!$AB:$AB,0))) | CD11: =IF(ISBLANK(AH11),"",INDEX(ValidationAndReference!$M:$M,MATCH(AH11,ValidationAndReference!$N:$N,0))) | CE11: =IF(ISBLANK(AI11),"",INDEX(ValidationAndReference!$AA:$AA,MATCH(AI11,ValidationAndReference!$AB:$AB,0))) | CF11: =IF(ISBLANK(AJ11),"",INDEX(ValidationAndReference!$M:$M,MATCH(AJ11,ValidationAndReference!$N:$N,0))) | CG11: =IF(ISBLANK(AU11),"",INDEX(ValidationAndReference!$S:$S,MATCH(AU11,ValidationAndReference!$T:$T,0))) | CH11: =IF(ISBLANK(AV11),"",INDEX(ValidationAndReference!$S:$S,MATCH(AV11,ValidationAndReference!$T:$T,0))) | CI11: =IF(ISBLANK(AW11),"",INDEX(ValidationAndReference!$S:$S,MATCH(AW11,ValidationAndReference!$T:$T,0))) | CJ11: =IF(ISBLANK(AX11),"",INDEX(ValidationAndReference!$S:$S,MATCH(AX11,ValidationAndReference!$T:$T,0))) | CK11: =IF(ISBLANK(AY11),"",INDEX(ValidationAndReference!$S:$S,MATCH(AY11,ValidationAndReference!$T:$T,0))) | CL11: =IFERROR(INDEX(ValidationAndReference!V:V, MATCH(AZ11, ValidationAndReference!W:W, 0)), "") | CM11: =IFERROR(INDEX(ValidationAndReference!V:V, MATCH(BA11, ValidationAndReference!W:W, 0)), "") | CN11: =IFERROR(INDEX(ValidationAndReference!V:V, MATCH(BB11, ValidationAndReference!W:W, 0)), "")
A12: Cleveland Amanda | B12: M | C12: Female | D12: MD | G12: OB-GYN | L12: Adult | M12: Intermountain Health UT - Central Women's Health | N12: =IFERROR(INDEX(Location!X:X, MATCH(BR12, Location!W:W, 0)), "") -> Intermountain Health UT - Central Women's Health Avenues Women's Center 370 E 9th Ave Ste 205 Salt Lake City UT (In Person) | O12: =IFERROR(INDEX(Location!X:X, MATCH(BS12, Location!W:W, 0)), "") -> Intermountain Health UT - Central Women's Health to be deleted -- New Harmony UT (Virtual) | P12: =IFERROR(INDEX(Location!X:X, MATCH(BT12, Location!W:W, 0)), "") | Q12: =IFERROR(INDEX(Location!X:X, MATCH(BU12, Location!W:W, 0)), "") | R12: =IFERROR(INDEX(Location!X:X, MATCH(BV12, Location!W:W, 0)), "") | S12: 1487815650 | T12: https://doctors.intermountainhealth.org/provider/amanda-m-cleveland/2561192 | BC12: pt_9sXRlV40j0GvSnpNVV7VRw | BE12: Practitioner - Full Profile | BG12: No | BI12: =IFERROR(INDEX(ValidationAndReference!P:P, MATCH(BE12, ValidationAndReference!Q:Q, 0)), "") -> 1 | BJ12: =IFERROR(INDEX(ValidationAndReference!F:F, MATCH(D12, ValidationAndReference!G:G, 0)), "") -> 1 | BK12: =IFERROR(INDEX(ValidationAndReference!F:F, MATCH(E12, ValidationAndReference!G:G, 0)), "") | BL12: =IFERROR(INDEX(ValidationAndReference!F:F, MATCH(F12, ValidationAndReference!G:G, 0)), "") | BM12: =IF(ISBLANK(G12),"",INDEX(ValidationAndReference!J:J,MATCH(G12,ValidationAndReference!K:K,0))) -> 104 | BN12: =IF(ISBLANK(H12),"",INDEX(ValidationAndReference!J:J,MATCH(H12,ValidationAndReference!K:K,0))) | BO12: =IF(ISBLANK(I12),"",INDEX(ValidationAndReference!J:J,MATCH(I12,ValidationAndReference!K:K,0))) | BP12: =IF(ISBLANK(J12),"",INDEX(ValidationAndReference!J:J,MATCH(J12,ValidationAndReference!K:K,0))) | BQ12: =IF(ISBLANK(K12),"",INDEX(ValidationAndReference!J:J,MATCH(K12,ValidationAndReference!K:K,0))) | BR12: lo_0P-S0R44AEypsKxmG4cTjR | BS12: lo_i9HrnJ3V80i8pDnVxHIE6A | BW12: =IF(ISBLANK(AA12),"",INDEX(ValidationAndReference!$AA:$AA,MATCH(AA12,ValidationAndReference!$AB:$AB,0))) | BX12: =IF(ISBLANK(AB12),"",INDEX(ValidationAndReference!$M:$M,MATCH(AB12,ValidationAndReference!$N:$N,0))) | BY12: =IF(ISBLANK(AC12),"",INDEX(ValidationAndReference!$AA:$AA,MATCH(AC12,ValidationAndReference!$AB:$AB,0))) | BZ12: =IF(ISBLANK(AD12),"",INDEX(ValidationAndReference!$M:$M,MATCH(AD12,ValidationAndReference!$N:$N,0))) | CA12: =IF(ISBLANK(AE12),"",INDEX(ValidationAndReference!$AA:$AA,MATCH(AE12,ValidationAndReference!$AB:$AB,0))) | CB12: =IF(ISBLANK(AF12),"",INDEX(ValidationAndReference!$M:$M,MATCH(AF12,ValidationAndReference!$N:$N,0))) | CC12: =IF(ISBLANK(AG12),"",INDEX(ValidationAndReference!$AA:$AA,MATCH(AG12,ValidationAndReference!$AB:$AB,0))) | CD12: =IF(ISBLANK(AH12),"",INDEX(ValidationAndReference!$M:$M,MATCH(AH12,ValidationAndReference!$N:$N,0))) | CE12: =IF(ISBLANK(AI12),"",INDEX(ValidationAndReference!$AA:$AA,MATCH(AI12,ValidationAndReference!$AB:$AB,0))) | CF12: =IF(ISBLANK(AJ12),"",INDEX(ValidationAndReference!$M:$M,MATCH(AJ12,ValidationAndReference!$N:$N,0))) | CG12: =IF(ISBLANK(AU12),"",INDEX(ValidationAndReference!$S:$S,MATCH(AU12,ValidationAndReference!$T:$T,0))) | CH12: =IF(ISBLANK(AV12),"",INDEX(ValidationAndReference!$S:$S,MATCH(AV12,ValidationAndReference!$T:$T,0))) | CI12: =IF(ISBLANK(AW12),"",INDEX(ValidationAndReference!$S:$S,MATCH(AW12,ValidationAndReference!$T:$T,0))) | CJ12: =IF(ISBLANK(AX12),"",INDEX(ValidationAndReference!$S:$S,MATCH(AX12,ValidationAndReference!$T:$T,0))) | CK12: =IF(ISBLANK(AY12),"",INDEX(ValidationAndReference!$S:$S,MATCH(AY12,ValidationAndReference!$T:$T,0))) | CL12: =IFERROR(INDEX(ValidationAndReference!V:V, MATCH(AZ12, ValidationAndReference!W:W, 0)), "") | CM12: =IFERROR(INDEX(ValidationAndReference!V:V, MATCH(BA12, ValidationAndReference!W:W, 0)), "") | CN12: =IFERROR(INDEX(ValidationAndReference!V:V, MATCH(BB12, ValidationAndReference!W:W, 0)), "")

Sheet Location
A1: Practice Name | B1: Location Name | C1: Location Type | D1: Address line 1 | E1: Address line 2 (Office/Suite #) | F1: City | G1: State | H1: ZIP Code | I1: Combined address | J1: Phone | K1: Ext. | L1: Fax | M1: Name of Contact Person | N1: Number of Providers | O1: Email for appointment notifications 1 | P1: Email for appointment notifications 2 | Q1: Email for appointment notifications 3 | R1: Email for appointment notifications 4 | S1: Virtual Visit Type | T1: Show name in search? | U1: Scheduling Software | V1: Practice Cloud ID | W1: Location Cloud ID | X1: Complete Location | Y1: Scheduling Software ID
A2: Intermountain Health UT - Central Women's Health | B2: Alta View Clinic - Women's Specialists | C2: In Person | D2: 9450 S 1300 E | F2: Sandy | G2: UT | H2: 84094 | I2: =D2&IF(E2<>"",", "&E2,"")&", "&F2&", "&G2&", "&H2 -> 9450 S 1300 E, Sandy, UT, 84094 | J2: 8014085555 | O2: practice.manager@zocdocusername.com | T2: Yes | U2: Epic | V2: pt_9sXRlV40j0GvSnpNVV7VRw | W2: lo_ZaDx5groBUmIgOlbOWKL-B | X2: =IF(A2<>"",CONCATENATE(A2," ",B2," ",D2," ",E2," ",F2," ",G2," ","(",C2,")"),"") -> Intermountain Health UT - Central Women's Health Alta View Clinic - Women's Specialists 9450 S 1300 E Sandy UT (In Person) | Y2: =IF(ISBLANK(U2),"",INDEX(ValidationAndReference!C:C,MATCH(U2,ValidationAndReference!D:D,0))) -> 427
A3: Intermountain Health UT - Central Women's Health | B3: to be deleted | C3: Virtual | D3: -- | F3: New Harmony | G3: UT | H3: 84757 | I3: =D3&IF(E3<>"",", "&E3,"")&", "&F3&", "&G3&", "&H3 -> --, New Harmony, UT, 84757 | J3: 8004417789 | O3: practice.manager@zocdocusername.com | S3: ThirdPartyVideoVisit | T3: Yes | U3: Epic | V3: pt_9sXRlV40j0GvSnpNVV7VRw | W3: lo_i9HrnJ3V80i8pDnVxHIE6A | X3: =IF(A3<>"",CONCATENATE(A3," ",B3," ",D3," ",E3," ",F3," ",G3," ","(",C3,")"),"") -> Intermountain Health UT - Central Women's Health to be deleted -- New Harmony UT (Virtual) | Y3: =IF(ISBLANK(U3),"",INDEX(ValidationAndReference!C:C,MATCH(U3,ValidationAndReference!D:D,0))) -> 427
A4: Intermountain Health UT - Central Women's Health | B4: Layton Parkway Clinic - Women's Health | C4: In Person | D4: 201 W Layton Pkwy | E4: Ste 2B | F4: Layton | G4: UT | H4: 84041 | I4: =D4&IF(E4<>"",", "&E4,"")&", "&F4&", "&G4&", "&H4 -> 201 W Layton Pkwy, Ste 2B, Layton, UT, 84041 | J4: 8014085555 | O4: practice.manager@zocdocusername.com | T4: Yes | U4: Epic | V4: pt_9sXRlV40j0GvSnpNVV7VRw | W4: lo_KOSlINdfhEmmNCQ0zLZpfB | X4: =IF(A4<>"",CONCATENATE(A4," ",B4," ",D4," ",E4," ",F4," ",G4," ","(",C4,")"),"") -> Intermountain Health UT - Central Women's Health Layton Parkway Clinic - Women's Health 201 W Layton Pkwy Ste 2B Layton UT (In Person) | Y4: =IF(ISBLANK(U4),"",INDEX(ValidationAndReference!C:C,MATCH(U4,ValidationAndReference!D:D,0))) -> 427
A5: Intermountain Health UT - Central Women's Health | B5: Avenues Women's Center | C5: In Person | D5: 370 E 9th Ave | E5: Ste 205 | F5: Salt Lake City | G5: UT | H5: 84103 | I5: =D5&IF(E5<>"",", "&E5,"")&", "&F5&", "&G5&", "&H5 -> 370 E 9th Ave, Ste 205, Salt Lake City, UT, 84103 | J5: 8014085555 | O5: practice.manager@zocdocusername.com | T5: Yes | U5: Epic | V5: pt_9sXRlV40j0GvSnpNVV7VRw | W5: lo_0P-S0R44AEypsKxmG4cTjR | X5: =IF(A5<>"",CONCATENATE(A5," ",B5," ",D5," ",E5," ",F5," ",G5," ","(",C5,")"),"") -> Intermountain Health UT - Central Women's Health Avenues Women's Center 370 E 9th Ave Ste 205 Salt Lake City UT (In Person) | Y5: =IF(ISBLANK(U5),"",INDEX(ValidationAndReference!C:C,MATCH(U5,ValidationAndReference!D:D,0))) -> 427
A6: Intermountain Health UT - Central Women's Health | B6: Bountiful Clinic - Women'S Health | C6: In Person | D6: 390 N Main St | F6: Bountiful | G6: UT | H6: 84010 | I6: =D6&IF(E6<>"",", "&E6,"")&", "&F6&", "&G6&", "&H6 -> 390 N Main St, Bountiful, UT, 84010 | J6: 8554427855 | O6: practice.manager@zocdocusername.com | T6: Yes | U6: Epic | V6: pt_9sXRlV40j0GvSnpNVV7VRw | W6: lo_2ly69_fZ50GORUzOt38fqR | X6: =IF(A6<>"",CONCATENATE(A6," ",B6," ",D6," ",E6," ",F6," ",G6," ","(",C6,")"),"") -> Intermountain Health UT - Central Women's Health Bountiful Clinic - Women'S Health 390 N Main St Bountiful UT (In Person) | Y6: =IF(ISBLANK(U6),"",INDEX(ValidationAndReference!C:C,MATCH(U6,ValidationAndReference!D:D,0))) -> 427
A7: Intermountain Health UT - Central Women's Health | B7: Southridge Clinic - OB/Gyn | C7: In Person | D7: 3723 W 12600 S | E7: Ste 360 | F7: Riverton | G7: UT | H7: 84065 | I7: =D7&IF(E7<>"",", "&E7,"")&", "&F7&", "&G7&", "&H7 -> 3723 W 12600 S, Ste 360, Riverton, UT, 84065 | J7: 8014085555 | O7: practice.manager@zocdocusername.com | T7: Yes | U7: Epic | V7: pt_9sXRlV40j0GvSnpNVV7VRw | W7: lo_YWHkLUhm8EOqqaiT6WcOnh | X7: =IF(A7<>"",CONCATENATE(A7," ",B7," ",D7," ",E7," ",F7," ",G7," ","(",C7,")"),"") -> Intermountain Health UT - Central Women's Health Southridge Clinic - OB/Gyn 3723 W 12600 S Ste 360 Riverton UT (In Person) | Y7: =IF(ISBLANK(U7),"",INDEX(ValidationAndReference!C:C,MATCH(U7,ValidationAndReference!D:D,0))) -> 427
A8: Intermountain Health UT - Central Women's Health | B8: Obstetrics & Gynecology Specialists | C8: In Person | D8: 5063 S Cottonwood St | E8: Ste 120 | F8: Murray | G8: UT | H8: 84107 | I8: =D8&IF(E8<>"",", "&E8,"")&", "&F8&", "&G8&", "&H8 -> 5063 S Cottonwood St, Ste 120, Murray, UT, 84107 | J8: 8554427855 | O8: practice.manager@zocdocusername.com | T8: Yes | U8: Epic | V8: pt_9sXRlV40j0GvSnpNVV7VRw | W8: lo_lPottpvJyEqiYFdt6pcgbh | X8: =IF(A8<>"",CONCATENATE(A8," ",B8," ",D8," ",E8," ",F8," ",G8," ","(",C8,")"),"") -> Intermountain Health UT - Central Women's Health Obstetrics & Gynecology Specialists 5063 S Cottonwood St Ste 120 Murray UT (In Person) | Y8: =IF(ISBLANK(U8),"",INDEX(ValidationAndReference!C:C,MATCH(U8,ValidationAndReference!D:D,0))) -> 427

Sheet ValidationAndReference
A1: State Lookup | C1: ID | D1: Software List | F1: ProfSuffixID | G1: Suffix | H1: Description | J1: Specialty ID | K1: Specialty Name | M1: ID | N1: Board Cetifications | P1: ProfTypeID | Q1: Profile Types | S1: Hospital ID | T1: Hopsital Name | V1: Lang ID | W1: Lang Descripton | Y1: Virtual Visit Type | AA1: ID | AB1: DisplayName | AD1: Practice Cloud ID | AE1: Practice Name
A2: AL | C2: 998 | D2: 4PatientCare | G2: Not Applicable | J2: 271 | K2: Abdominal Radiologist | M2: 170 | N2: Addiction Medicine (American Osteopathic Board of Family Physicians) | P2: 1 | Q2: Practitioner - Full Profile | S2: 6984 | T2: , A Steward Family Hospital | V2: 1 | W2: English | Y2: ZocdocVideoVisit | AA2: 1 | AB2: Critical Care Medicine (Anesthesiology) | AD2: pt_9sXRlV40j0GvSnpNVV7VRw | AE2: Intermountain Health UT - Central Women's Health
A3: AK | C3: 499 | D3: A2C | F3: 1 | G3: MD | H3: Medical Doctor | J3: 345 | K3: Acupuncturist | M3: 150 | N3: Alliance for Physician Certification & Advancement | P3: 11 | Q3: Facility | S3: 1770 | T3: 10th Medical Group, United States Air Force Academy Hospital | V3: 2 | W3: French | Y3: ThirdPartyVideoVisit | AA3: 2 | AB3: Hospice and Palliative Care (Anesthesiology)
A4: AZ | C4: 528 | D4: Abraxas | F4: 2 | G4: DDS | H4: Doctor of Dental Surgery | J4: 418 | K4: Acute Care Nurse Practitioner (Adult / Gerontology) | M4: 95 | N4: American Academy of Chiropractic Orthopedics | P4: 3 | Q4: Dental Hygienist - Bookable Resource | S4: 1771 | T4: 1st Medical Group - Langley Air Force Base | V4: 3 | W4: Spanish | AA4: 3 | AB4: Pain Medicine (Anesthesiology)
A5: AR | C5: 463 | D5: ABS | F5: 3 | G5: OD | H5: Doctor of Optometry (Oculus Doctor) | J5: 446 | K5: Acute Care Nurse Practitioner (Pediatric) | M5: 163 | N5: American Academy of Manipulative Therapy | P5: 9 | Q5: Nurse - Bookable Resource | S5: 1772 | T5: 366th Medical Group - Mountain Home Air Force Base | V5: 4 | W5: German | AA5: 4 | AB5: Clinical & Laboratory Dermatological Immunology (Dermatology)
A6: CA | C6: 774 | D6: Accenta | F6: 4 | G6: DO | H6: Doctor of Osteopathy | J6: 298 | K6: Addiction Specialist | M6: 166 | N6: American Academy of Nurse Practitioners National Certification Board | P6: 10 | Q6: Resident - Bookable Resource | S6: 1773 | T6: 375th Medical Group - Scott Air Force Base Medical Center | V6: 5 | W6: Hebrew | AA6: 5 | AB6: Dermatopathology (Dermatology)
A7: CO | C7: 236 | D7: Accumed | F7: 5 | G7: DMD | H7: Doctor of Medical Dentistry | J7: 253 | K7: Adolescent Medicine Specialist | M7: 54 | N7: American Board Electrodiagnostic Medicine | P7: 4 | Q7: Therapist - Bookable Resource | S7: 1774 | T7: 3rd Medical Group - United States Air Force Regional Hospital | V7: 6 | W7: Farsi | AA7: 6 | AB7: Pediatric Dermatology (Dermatology)
A8: CT | C8: 501 | D8: Ace Dental | F8: 6 | G8: FACOG | H8: Fellow of the American College of Obstetricians and Gynecologists | J8: 432 | K8: Adult Congenital Heart Disease Specialist | M8: 119 | N8: American Board for Certification in Orthotics Prosthetics and Pedorthics | P8: 6 | Q8: Nurse Practitioner - Bookable Resource | S8: 1775 | T8: 60th Medical Group - David Grant USAF Medical Center | V8: 7 | W8: Italian | AA8: 7 | AB8: Hospice and Palliative Care (Emergency Medicine)
A9: DE | C9: 801 | D9: Acom | F9: 7 | G9: DPM | H9: Doctor of Podiatric Medicine | J9: 400 | K9: Adult Nurse Practitioner | M9: 53 | N9: American Board of Addiction Medicine | P9: 2 | Q9: Physician Assistant - Bookable Resource | S9: 1776 | T9: 6th Medical Group - MacDill Air Force Base | V9: 10 | W9: Arabic | AA9: 8 | AB9: Medical Toxicology (Emergency Medicine)
A10: DC | C10: 465 | D10: Acrendo | F10: 8 | G10: FACS | H10: Fellow of the American College of Surgeons | J10: 405 | K10: Adult Psychiatric & Mental Health Nurse Practitioner | M10: 18 | N10: American Board of Allergy and Immunology | S10: 1777 | T10: 81st Medical Group - Keesler Medical Center | V10: 11 | W10: Hindi | AA10: 9 | AB10: Pediatric Emergency Medicine (Emergency Medicine)
A11: FL | C11: 376 | D11: ACT | F11: 9 | G11: PhD | H11: Doctor of Philosophy | J11: 439 | K11: Adult Reconstructive Orthopedic Surgeon | M11: 1 | N11: American Board of Anesthesiology | S11: 1778 | T11: 88th Medical Group - Wright-Patterson Air Force Base Medical Center | V11: 12 | W11: Urdu | AA11: 10 | AB11: Sports Medicine (Emergency Medicine)
A12: GA | C12: 934 | D12: Acuity Scheduling | F12: 10 | G12: FACC | H12: Fellow of the American College of Cardiology | J12: 422 | K12: Advanced Heart Failure and Transplant Cardiologist | M12: 87 | N12: American Board Of Anti-Aging & Regenerative Medicine | S12: 1779 | T12: 96th Medical Group - United States Air Force Regional Hospital | V12: 13 | W12: Dutch | AA12: 11 | AB12: Undersea and Hyperbaric Medicine (Emergency Medicine)
A13: GU | C13: 718 | D13: Adaptamed | F13: 11 | G13: MPH | H13: Master of Public Health | J13: 160 | K13: Aesthetic Surgeon | M13: 85 | N13: American Board of Audiology | S13: 1780 | T13: 99th Medical Group, Mike O'Callaghan Federal Hospital | V13: 14 | W13: Vietnamese | AA13: 12 | AB13: Adolescent Medicine (Family Medicine)
A14: HI | C14: 226 | D14: ADS Medix Elite | F14: 12 | G14: FAAD | H14: Fellow of the American Academy of Dermatology | J14: 564 | K14: Aesthetician / Esthetician | M14: 77 | N14: American Board of Bariatric Medicine | S14: 1781 | T14: A.G. Holley State Hospital | V14: 15 | W14: Russian | AA14: 13 | AB14: Geriatric Medicine (Family Medicine)
A15: ID | C15: 362 | D15: ADS Medix Premier | F15: 13 | G15: FAAP | H15: Fellow of the American Academy of Pediatrics | J15: 132 | K15: Allergist | M15: 94 | N15: American Board of Chiropractic Internists | S15: 1782 | T15: A.L. Lee Memorial Hospital | V15: 16 | W15: Portuguese | AA15: 14 | AB15: Hospice and Palliative Care (Family Medicine)
A16: IL | C16: 819 | D16: Advanced Data Systems | F16: 14 | G16: AACFAS | H16: Associate of the American College of Foot and Ankle Surgeons | J16: 145 | K16: Anesthesiologist | M16: 80 | N16: American Board of Clinical Lipidology | S16: 60 | T16: A.O. Fox Hospital | V16: 17 | W16: Bengali | AA16: 15 | AB16: Sleep Medicine (Family Medicine)
A17: IN | C17: 961 | D17: Advanced MD | F17: 15 | G17: ACNP-BC | H17: Acute Care Nurse Practitioner - Board Certified | J17: 346 | K17: Audiologist | M17: 19 | N17: American Board of Colon and Rectal Surgery | S17: 1783 | T17: Abbeville Area Medical Center | V17: 18 | W17: Japanese | AA17: 16 | AB17: Sports Medicine (Family Medicine)
A18: IA | C18: 328 | D18: AdvancedMD | F18: 16 | G18: ACNPC-AG | H18: Acute Care Nurse Practitioner Certified | J18: 364 | K18: Bariatric Physician | M18: 52 | N18: American Board of Cosmetic Surgery | S18: 1784 | T18: Abbeville General Hospital | V18: 19 | W18: Javanese | AA18: 17 | AB18: Adolescent Medicine (Internal Medicine)
A19: KS | C19: 866 | D19: advantachart | F19: 17 | G19: AGAF | H19: Fellow of the American Gastroenterological Association | J19: 256 | K19: Bariatric Surgeon | M19: 27 | N19: American Board of Dental Public Health | S19: 1 | T19: Abbott Northwestern Hospital | V19: 20 | W19: Telugu | AA19: 18 | AB19: Cardiovascular Disease (Internal Medicine)
A20: KY | C20: 511 | D20: Advantage EMR | F20: 18 | G20: AGPCNP | H20: Adult-Gerontology Primary Care Nurse Practitioner | J20: 509 | K20: Behavior Analyst | M20: 147 | N20: American Board of Dental Sleep Medicine | S20: 1785 | T20: Aberdeen Area Indian Health Service | V20: 21 | W20: Marathi | AA20: 19 | AB20: Clinical Cardiac Electrophysiology (Internal Medicine)
A21: LA | C21: 225 | D21: AdvantX | F21: 19 | G21: ANP | H21: Advanced Nurse Practitioner | J21: 239 | K21: Behavioral Pediatrics Specialist | M21: 2 | N21: American Board of Dermatology | S21: 1786 | T21: Abilene Regional Medical Center | V21: 22 | W21: Korean | AA21: 20 | AB21: Critical Care Medicine (Internal Medicine)
... A55: WY | C55: 907 | D55: Aprima 2014 | F55: 52 | G55: DAc | H55: Doctor of Acupuncture | J55: 457 | K55: Diabetes Educator | M55: 107 | N55: American Board of Oral Implantology / Implant Dentistry | S55: 1808 | T55: Advanced Care Hospital of Montana | V55: 92 | W55: Uzbek | AA55: 54 | AB55: Molecular Genetic Pathology (Pathology)
C56: 870 | D56: Ariel Medical | F56: 53 | G56: DAOM | H56: Doctor of Acupuncture and Oriental Medicine | J56: 431 | K56: Diagnostic Radiologist | M56: 31 | N56: American Board of Orthodontics | S56: 1809 | T56: Advanced Care Hospital of Southern New Mexico | V56: 93 | W56: Sindhi | AA56: 55 | AB56: Neuropathology (Pathology)
C57: 524 | D57: ASP Medical | F57: 54 | G57: DC | H57: Doctor of Chiropractic | J57: 359 | K57: Dietitian | M57: 8 | N57: American Board of Orthopaedic Surgery | S57: 1810 | T57: Advanced Care Hospital of White County | V57: 94 | W57: Yoruba | AA57: 56 | AB57: Pediatric Pathology (Pathology)
C58: 932 | D58: ASPC | F58: 55 | G58: DiplAc | H58: Diplomate in Acupuncture | J58: 130 | K58: Ear, Nose & Throat Doctor | M58: 9 | N58: American Board of Otolaryngology | S58: 7126 | T58: Advanced Diagnostics Hospital East | V58: 95 | W58: Somali | AA58: 57 | AB58: Adolescent Medicine (Pediatrics)
C59: 969 | D59: Aspire | F59: 56 | G59: DM | H59: Doctor of Management | J59: 414 | K59: Elbow Surgeon | M59: 148 | N59: American Board of Otolaryngology - Head and Neck Surgery | S59: 1811 | T59: Advanced Healthcare Medical Center | V59: 96 | W59: Lao | AA59: 58 | AB59: Child Abuse Pediatrics (Pediatrics)
C60: 218 | D60: Athena | F60: 57 | G60: DMin | H60: Doctor of Ministry | J60: 146 | K60: Emergency Medicine Physician | M60: 65 | N60: American Board of Pain Medicine | S60: 3103 | T60: AdventHealth East Orlando | V60: 97 | W60: Cebuano | AA60: 59 | AB60: Developmental-Behavioral Pediatrics (Pediatrics)
C61: 902 | D61: Athena API | F61: 57 | G61: DMin | H61: Doctor of Ministry | J61: 419 | K61: Endocrine Surgeon | M61: 10 | N61: American Board of Pathology | S61: 6988 | T61: AdventHealth Tampa | V61: 98 | W61: Malay | AA61: 60 | AB61: Hospice and Palliative Care (Pediatrics)
C62: 921 | D62: AtlasMD | F62: 58 | G62: DMSc | H62: Doctor of Medical Science | J62: 127 | K62: Endocrinologist | M62: 32 | N62: American Board of Pediatric Dentistry | S62: 6906 | T62: AdventHealth Winter Park | V62: 99 | W62: Igbo | AA62: 61 | AB62: Medical Toxicology (Pediatrics)
C63: 601 | D63: Atom8 | F63: 59 | G63: DNP | H63: Doctor of Nursing Practice | J63: 134 | K63: Endodontist | M63: 11 | N63: American Board of Pediatrics | S63: 1240 | T63: Adventist HealthCare Shady Grove Medical Center | V63: 100 | W63: Malagasy | AA63: 62 | AB63: Neonatal-Perinatal Medicine (Pediatrics)
C64: 691 | D64: AUDserv | F64: 60 | G64: DNSc | H64: Doctor of Nursing Science | J64: 428 | K64: Endovascular Surgical Neuroradiologist | M64: 25 | N64: American Board of Periodontology | S64: 7267 | T64: Adventist HealthCare White Oak Medical Center | V64: 101 | W64: Nepali | AA64: 63 | AB64: Neurodevelopmental Disabilities (Pediatrics)
C65: 435 | D65: Augusta | F65: 61 | G65: DOM | H65: Doctor of Oriental Medicine | J65: 394 | K65: Epilepsy Specialist | M65: 12 | N65: American Board of Physical Medicine and Rehabilitation | S65: 1814 | T65: Adventist Medical Center | V65: 102 | W65: Assamese | AA65: 64 | AB65: Pediatric Cardiology (Pediatrics)
C66: 581 | D66: AutoMed | F66: 62 | G66: DPT | H66: Doctor of Physical Therapy | J66: 167 | K66: Facial Plastic & Reconstructive Surgeon | M66: 108 | N66: American Board of Physical Therapy Specialties | S66: 1815 | T66: Adventist Rehabilitation Hospital of Maryland | V66: 103 | W66: Shona | AA66: 65 | AB66: Pediatric Critical Care Medicine (Pediatrics)
C67: 707 | D67: Autumn8 | F67: 63 | G67: DSC | H67: Doctor of Science | J67: 401 | K67: Family Nurse Practitioner | M67: 98 | N67: American Board of Physician Nutrition Specialists | S67: 1816 | T67: Advocate Bethany Hospital | V67: 104 | W67: Khmer | AA67: 66 | AB67: Pediatric Emergency Medicine (Pediatrics)
... C144: 652 | D144: Customer Appointment Manager | F144: 133 | G144: MN | H144: Master of Nursing | J144: 519 | K144: Nurse Practitioner (Cardiology) | M144: 149 | N144: Art Therapy Credentials Board | S144: 1860 | T144: Amarillo VA Health Care System - Thomas E. Creek VA Medical Center | V144: 185 | W144: Serbian | AA144: 120 | AB144: Infectious Disease (Internal Medicine)
C145: 849 | D145: CX Service | F145: 134 | G145: MPA | H145: Master of Public Administration | J145: 557 | K145: Nurse Practitioner (Chiropractic) | M145: 168 | N145: Behavior Analyst Certification Board | S145: 40 | T145: American Fork Hospital | AA145: 121 | AB145: Nephrology (Internal Medicine)
C146: 708 | D146: Cybax | F146: 135 | G146: MPT | H146: Master of Physical Therapy | J146: 522 | K146: Nurse Practitioner (Dermatology) | M146: 169 | N146: Board Certified Specialist in Gerontological Nutrition (CSG) (Commission on Dietetic Registration) | S146: 1861 | T146: American Legion Hospital | AA146: 122 | AB146: Oncology (Internal Medicine)
C147: 685 | D147: Cycle | F147: 136 | G147: MRCP | H147: Membership of the Royal College of Physicians | J147: 524 | K147: Nurse Practitioner (ENT) | M147: 81 | N147: Certification Board of Cardiovascular Computed Tomography | S147: 1862 | T147: Amery Regional Medical Center | AA147: 123 | AB147: Pulmonary Diseases (Internal Medicine)
C148: 437 | D148: Cyclops | F148: 137 | G148: MS | H148: Master of Science | J148: 525 | K148: Nurse Practitioner (Gastroenterology) | M148: 43 | N148: Certification Board of Nuclear Cardiology | S148: 1812 | T148: AMITA Health Adventist Medical Center Bolingbrook | AA148: 124 | AB148: Rheumatology (Internal Medicine)
C149: 512 | D149: CynaMed | F149: 138 | G149: MSD | H149: Master of Science in Dentistry | J149: 556 | K149: Nurse Practitioner (Hepatology) | M149: 172 | N149: Certified Clinician - (DBT - Linehan Board of Certification) | S149: 1813 | T149: AMITA Health Adventist Medical Center GlenOaks | AA149: 125 | AB149: Addiction Medicine (Internal Medicine)
C150: 457 | D150: Cytrix Touchworks | F150: 139 | G150: MSN | H150: Master's of Science in Nursing | J150: 546 | K150: Nurse Practitioner (Neurology) | M150: 91 | N150: Chiropractic Board of Clinical Nutrition | S150: 6 | T150: AMITA Health Adventist Medical Center Hinsdale | AA150: 126 | AB150: Clinical Cardiac Electrophysiology (Internal Medicine)
C151: 800 | D151: Daisy | F151: 140 | G151: MSOM | H151: Master of Science in Oriental Medicine | J151: 523 | K151: Nurse Practitioner (OB-GYN) | M151: 162 | N151: Commission on Dietetic Registration | S151: 699 | T151: AMITA Health Adventist Medical Center La Grange | AA151: 127 | AB151: Critical Care Medicine (Internal Medicine)
C152: 347 | D152: DAQ | F152: 141 | G152: MSTOM | H152: Master of Science in Traditional Oriental Medicine | J152: 548 | K152: Nurse Practitioner (Oncology) | M152: 167 | N152: Dermatology Nurse Practitioner Certification Board | S152: 1863 | T152: Anaheim General Hospital | AA152: 128 | AB152: Geriatric Medicine (Internal Medicine)
C153: 999 | D153: Data Team DDS | F153: 142 | G153: MSW | H153: Master of Social Work | J153: 550 | K153: Nurse Practitioner (Orthopedics) | M153: 114 | N153: International Board of Chiropractic Neurology | S153: 7097 | T153: Anaheim Global Medical Center | AA153: 129 | AB153: Hospice and Palliative Medicine (Internal Medicine)
C154: 827 | D154: Database | F154: 143 | G154: ND | H154: Naturopathic Doctor | J154: 526 | K154: Nurse Practitioner (Pain Management) | M154: 153 | N154: International Board of Lactation Consultant Examiners | S154: 41 | T154: Anaheim Memorial Medical Center | AA154: 130 | AB154: Interventional Cardiology (Internal Medicine)
C155: 348 | D155: DataCon | F155: 144 | G155: NMD | H155: Naturopathic Medical Doctor | J155: 552 | K155: Nurse Practitioner (Pediatrics) | M155: 173 | N155: Kaltenborn-Evjenth Orthopaedic Manual Physical Therapy | S155: 6982 | T155: Anaheim Regional Medical Center | AA155: 131 | AB155: Sleep Medicine (Internal Medicine)
C156: 856 | D156: Davinci Virtual | F156: 145 | G156: NP | H156: Nurse Practitioner | J156: 529 | K156: Nurse Practitioner (Podiatry) | M156: 88 | N156: National Board for Certification in Hearing Instrument Sciences | S156: 1864 | T156: Anchor Hospital | AA156: 132 | AB156: Sports Medicine (Internal Medicine)
C157: 1000 | D157: DayClips | F157: 146 | G157: NTP | H157: Nutritional Therapy Practitioner | J157: 531 | K157: Nurse Practitioner (Psychiatry) | M157: 152 | N157: National Board for Certification in Occupational Therapy | S157: 1865 | T157: Ancora Psychiatric Hospital
C158: 670 | D158: DBS | F158: 147 | G158: OCS | H158: Orthopedic Clinical Specialist | J158: 554 | K158: Nurse Practitioner (Psychology) | M158: 154 | N158: National Board for Certified Counselors | S158: 1866 | T158: Andalusia Regional Hospital
C159: 613 | D159: Dejawin | F159: 147 | G159: OCS | H159: Orthopedic Clinical Specialist | J159: 559 | K159: Nurse Practitioner (Psychotherapy) | M159: 99 | N159: National Board of Chiropractic Examiners | S159: 1867 | T159: Anderson County Hospital
C160: 761 | D160: denicon | F160: 148 | G160: OTR | H160: Occupational Therapist Registered | J160: 558 | K160: Nurse Practitioner (Pulmonology) | M160: 34 | N160: National Board of Echocardiography | S160: 1868 | T160: Anderson Hospital
C161: 700 | D161: Dentacon | F161: 149 | G161: OCS | H161: Ophthalmic Coding Specialist | J161: 555 | K161: Nurse Practitioner (Rheumatology) | M161: 103 | N161: National Board of Examiners in Optometry | S161: 1869 | T161: Androscoggin Valley Hospital
C162: 956 | D162: Dental Office Xpress (DOX) | F162: 150 | G162: OMD | H162: Oriental Medicine Doctor | J162: 533 | K162: Nurse Practitioner (Sleep Medicine) | M162: 118 | N162: National Board of Physician Nutrition Specialists | S162: 1870 | T162: Angel Medical Center
C163: 609 | D163: Dental-Exec | F163: 151 | G163: PA | H163: Physician Assistant | J163: 527 | K163: Nurse Practitioner (Urology) | M163: 115 | N163: National Board of Physicians and Surgeons | S163: 1871 | T163: Angela Jane Pavillion
C164: 636 | D164: DentalMate | F164: 152 | G164: PA-C | H164: Physician Assistant-Certified | J164: 530 | K164: Nurse Practitioner (Vascular Surgery) | M164: 89 | N164: National Certification Board for Diabetes Educators | S164: 1872 | T164: Angleton Danbury Medical Center
C165: 878 | D165: dentalpro | F165: 153 | G165: PharmD | H165: Doctor of Pharmacy | J165: 384 | K165: Nutritionist | M165: 84 | N165: National Certification Commission for Acupuncture and Oriental Medicine | S165: 1873 | T165: Animas Surgical Hospital
C166: 591 | D166: DentalVision | F166: 154 | G166: PMH | H166: Psychiatric/Mental Health Nurse | J166: 104 | K166: OB-GYN | M166: 145 | N166: National Commission on Certification of Physician Assistants | S166: 42 | T166: AnMed Health
C167: 358 | D167: Dentamax | F167: 155 | G167: PsyD | H167: Doctor of Psychology | J167: 487 | K167: OB-GYN - Resident | M167: 61 | N167: National Dental Board of Anesthesiology | S167: 1874 | T167: AnMed HealthSouth Rehabilitation Hospital
C168: 502 | D168: Dentaweb | F168: 156 | G168: PNS | H168: Physician Nutrition Specialist | J168: 404 | K168: OB-GYN Nurse Practitioner | M168: 174 | N168: Orthopaedic Manual Physical Therapy | S168: 7068 | T168: Ann & Robert H. Lurie Children's Hospital of Chicago
... C170: 539 | D170: Denticon | F170: 158 | G170: QME | H170: Qualified Medical Evaluator | J170: 469 | K170: Obstetrician | M170: 151 | N170: Registered Physician in Vascular Interpretation | S170: 1876 | T170: Anna Jaques Hospital
C171: 743 | D171: Dentimax | F171: 159 | G171: RAc | H171: Registered Acupuncturist | J171: 357 | K171: Occupational Medicine Specialist | N171: American Board of Physician Specialties (Geriatric Medicine) | S171: 43 | T171: Anne Arundel Medical Center
C172: 692 | D172: Dentisoft | F172: 160 | G172: RD | H172: Registered Dietitian | J172: 374 | K172: Occupational Therapist | N172: American Board of Physician Specialties (Hospital Medicine) | S172: 1877 | T172: Annie Jeffrey Memorial County Health Center
C173: 945 | D173: DentOffice | F173: 161 | G173: RDH | H173: Registered Dental Hygienist | J173: 176 | K173: Ocular Oncologist | N173: American Board of Physician Specialties (Integrative Medicine) | S173: 1878 | T173: Annie Penn Hospital
C174: 379 | D174: Dentrix | F174: 162 | G174: RDN | H174: Registered Dietitian Nutritionist | J174: 177 | K174: Ocular Pathologist | N174: American Board of Physician Specialties (Internal Medicine) | S174: 1879 | T174: Anoka-Metro Regional Treatment Center
C175: 939 | D175: Dentrix Ascend | F175: 163 | G175: RN | H175: Registered Nurse | J175: 186 | K175: Oculoplastic Surgeon | N175: American Board of Physician Specialties (Obstetrics & Gynecology) | S175: 1880 | T175: Anson Community Hospital
C176: 875 | D176: Dentrix Enterprise | F176: 164 | G176: RPh | H176: Registered Pharmacist | J176: 111 | K176: Oncologist | N176: American Board of Physician Specialties (Ophthalmology) | S176: 1881 | T176: Anson General Hospital
C177: 1016 | D177: Dentrix Enterprise 8 | F177: 165 | G177: RVT | H177: Registered Vascular Technologist | J177: 450 | K177: Oncology Nurse Practitioner (Adult / Gerontology) | N177: American Board of Physician Specialties (Orthopedic Surgery) | S177: 1882 | T177: Antelope Memorial Hospital
C178: 755 | D178: Dentrix G4 | F178: 166 | G178: SLP | H178: Speech-Language Pathologist | J178: 451 | K178: Oncology Nurse Practitioner (Pediatric) | N178: American Board of Physician Specialties (Plastic & Reconstructive Surgery) | S178: 44 | T178: Antelope Valley Hospital
C179: 632 | D179: Dentrix G5 | F179: 167 | G179: WHNP | H179: Women's Health Nurse Practitioner | J179: 179 | K179: Ophthalmic Pathologist | N179: American Board of Physician Specialties (Psychiatry) | S179: 1883 | T179: Antioch Medical Center
C180: 909 | D180: Dentrix G6 | F180: 168 | G180: LCAT | H180: Licensed Creative Arts Therapist | J180: 178 | K180: Ophthalmic Plastic, Orbital & Reconstructive Surgeon | N180: American Board of Physician Specialties (Radiation Oncology) | S180: 1884 | T180: Apalachee Center, Inc.
C181: 1022 | D181: Dentrix G7 | F181: 169 | G181: DCNP | H181: Dermatology Certified Nurse Practitioner | J181: 116 | K181: Ophthalmologist | N181: American Board of Physician Specialties (Surgery) | S181: 1885 | T181: Apex Hospital - Houston
C182: 611 | D182: Denturist Office Manager (DOM) | F182: 170 | G182: MHA | H182: Master of Health Administration | J182: 376 | K182: Optometric Glaucoma Specialist | N182: American Board of Physician Specialties (Urgent Care) | S182: 1886 | T182: Apex Hospital - Katy
... C294: 276 | D294: Google Calendar | F294: 279 | G294: NE - BC | H294: Nurse Executive Board Certified | J294: 322 | K294: Toxicologist | N294: National Dental Board of Anesthesiology | S294: 73 | T294: Avera McKennan Hospital & University Health Center
C295: 245 | D295: Greenway | F295: 280 | G295: RNC - OB | H295: Inpatient Obstetric Nursing | J295: 435 | K295: Transplant Hepatologist | S295: 1965 | T295: Avera Queen of Peace Hospital
C296: 894 | D296: H Chart | F296: 281 | G296: C - EFM | H296: Certification in Electronic Fetal Monitoring | J296: 326 | K296: Transplant Specialist | S296: 74 | T296: Avera Sacred Heart Hospital
C297: 825 | D297: Handyworks | F297: 282 | G297: RPA - C | H297: Registered Physician Assistant - Certified | J297: 258 | K297: Trauma Surgeon | S297: 1966 | T297: Avera Saint Anthony's Hospital
C298: 542 | D298: Harmony | F298: 283 | G298: LMFC | H298: Licensed Marriage and Family Counselor | J298: 343 | K298: Travel Medicine Specialist | S298: 1967 | T298: Avera Saint Benedict Hospital
C299: 717 | D299: HCIT | F299: 284 | G299: APNP | H299: Advanced Practice Nurse Prescriber | J299: 570 | K299: Ultrasound Facility | S299: 75 | T299: Avera Saint Luke's Hospital
C300: 558 | D300: H-DOX | F300: 285 | G300: CSAC | H300: Clinical Substance Abuse Counselor | J300: 513 | K300: Urgent Care Clinic | S300: 1968 | T300: Avera Weskota Memorial Medical Center
C301: 398 | D301: Health Highway | F301: 286 | G301: CSIT | H301: Clinical Supervisor In Training | J301: 237 | K301: Urogynecologist | S301: 76 | T301: Avista Adventist Hospital
C302: 380 | D302: Health Options | F302: 287 | G302: BSN | H302: Bachelor of Science in Nursing | J302: 408 | K302: Urological Surgeon | S302: 1969 | T302: Avoyelles Hospital
C303: 450 | D303: HealthFusion | F303: 288 | G303: CDCES | H303: Certified Diabetes Care and Education Specialist | J303: 126 | K303: Urologist | S303: 1970 | T303: Bacharach Institute for Rehabilitation
C304: 1038 | D304: Healthie | F304: 289 | G304: LDS | H304: License of Dental Surgery | J304: 213 | K304: Uveitis Specialist | S304: 1971 | T304: Bacon County Hospital
C305: 452 | D305: HealthNautica | F305: 290 | G305: MDS | H305: Master of Dental Surgery | J305: 429 | K305: Vascular Interventional Radiologist | S305: 1972 | T305: Bailey Medical Center
C306: 862 | D306: Healthpac | F306: 291 | G306: LSCSW | H306: Licensed Specialist Clinical Social Worker | J306: 319 | K306: Vascular Neurology Specialist | S306: 1973 | T306: Bakersfield Heart Hospital
... C311: 699 | D311: HearForum | F311: 296 | G311: CPT | H311: Certified Personal Trainer | J311: 567 | K311: X-Ray Facility | S311: 1976 | T311: Ballinger Memorial Hospital
C312: 688 | D312: HearSoft | F312: 296 | G312: CPT | H312: Certified Personal Trainer | S312: 80 | T312: Baltimore Washington Medical Center
C313: 425 | D313: Helios | F313: 297 | G313: DSC | H313: Doctor of Surgical Chiropody | S313: 1977 | T313: Bamberg County Hospital
C314: 747 | D314: Hello Health | F314: 298 | G314: NM | H314: Nurse Midwife | S314: 1634 | T314: Banner Baywood Medical Center
C315: 781 | D315: Hima | F315: 299 | G315: CAC III | H315: Certified Addiction Counselor III | S315: 82 | T315: Banner Behavioral Health Hospital - Scottsdale
C316: 797 | D316: HMS | F316: 300 | G316: LP | H316: Licensed Psychologist | S316: 1494 | T316: Banner Boswell Medical Center
C317: 580 | D317: Horizon Practice Plus | F317: 301 | G317: RYT | H317: Registered Yoga Teacher | S317: 1978 | T317: Banner Churchill Community Hospital
C318: 931 | D318: HSWorx | F318: 302 | G318: CAC II | H318: Certified Addiction Counselor II | S318: 1495 | T318: Banner Del E. Webb Medical Center
C319: 643 | D319: ICANotes | F319: 303 | G319: FAAPMR | H319: Fellow of the American Academy of Physical Medicine and Rehabilitation | S319: 83 | T319: Banner Desert Medical Center
C320: 851 | D320: iClaim | F320: 304 | G320: RPhS | H320: Registered Phlebology Sonographer | S320: 1979 | T320: Banner Estrella Medical Center
C321: 269 | D321: Iclinics | F321: 305 | G321: LCMHCS | H321: Licensed Clinical Mental Health Counselor Supervisor | S321: 1980 | T321: Banner Gateway Medical Center
C322: 271 | D322: ICS | F322: 306 | G322: LCSWA | H322: Licensed Clinical Social Worker Associate | S322: 84 | T322: Banner Good Samaritan Medical Center
C323: 784 | D323: Ideal | F323: 307 | G323: LMFTA | H323: Licensed Marriage and Family Therapy Associate | S323: 81 | T323: Banner Heart Hospital
... C511: 438 | D511: Opal-Rad | F511: 494 | G511: DPC | H511: Doctor of Professional Counseling | S511: 2101 | T511: Benton Rehabilitation Hospital
C512: 338 | D512: OpenDental | S512: 46 | T512: Bergan Mercy Medical Center
...
